Workbook

Sheet Summary
A1: The Council — Agent Record (Agentic System Bill of Materials, ASBOM)
A2: AIG-AGT-04 · v0.7 working draft · Draft for Council review · OFFICIAL · ISO/IEC 42001:2023 · OWASP 2026-aligned
A3: Purpose: the core per-agent record of the agentic layer. One agent, one row on Agent Record, keyed to the permanent AIR-ID plus the agent’s AG-ID; every child sheet carries both keys. The Capability Vector, Components (bill of materials) and Authority & Delegations sheets add the detail an agent's row cannot hold. The AI Register (AIG-INV-04) becomes the portfolio index that points here. Governs the authority envelope (what the agent can do), not the intended use.
A4: Controlled identifier status | B4: AIG-AGT-04 (controlled identifier; formal Council adoption pending)
A6: Field | B6: Controlled value
A7: Document ID | B7: AIG-AGT-04
A8: Version | B8: 0.7 working draft
A9: Status | B9: Draft for Council review; nothing evidenced until operated
A10: Owner | B10: AI Governance Lead; operational and technical owners retain delivery responsibilities
A11: Date | B11: 16 October 2026
A12: Built to | B12: Agentic AI Governance Design Principles (AIG-AGT-01; core principle + five invariants)
A13: Source | B13: OWASP Top 10 for Agentic Applications 2026 (ASI01-ASI10); OWASP Agent Control Standard (1 Sep 2026)
A14: Relationship | B14: AI Register (AIG-INV-04) indexes this; Authority & Delegations feeds the Agent Authority Graph; Agentic Triage records the assessed autonomy level and Agency Tier; the permitted autonomy level is granted at Gate 6 (go-live) by the delegated decision (AIG-DEC-03); each agency tier sets a minimum risk-tier pathway (Gate Map AIG-DEC-01, Agentic pathway)
A15: Classification | B15: OFFICIAL
A17: Change history
A18: Version | B18: Date — change
A19: 0.2 working draft | B19: 25 September 2026 — working draft (history entry reconstructed during QA remediation).
A20: 0.3 working draft | B20: 29 September 2026 — QA remediation — applied findings QA-053, QA-057, QA-094, QA-127, QA-128, QA-129, QA-210, QA-226, QA-227, QA-228, QA-233, QA-234, QA-235, QA-240, QA-251, QA-252, QA-272, QA-280, QA-284, QA-288, QA-291, QA-292 (see QA change log). AG-ID added to every child sheet; ASBOM record version, agency profile, tier floor, pathway and oversight fields added; lists realigned and wired to validations. v3.7 alignment (no version change): permitted autonomy granted at Gate 6; governing pathway = higher of risk-tier pathway and agency-tier minimum (AIG-DEC-01 Agentic pathway); equivalent-control authorisation evidenced at Gate 2 and re-confirmed at Gate 6; “Production gate” label renamed “Production requirement (checked at Gate 6)”.
A21: 0.4 working draft | B21: 30 September 2026 — v3.9.2: Record QA (Agent Record BI) now requires each Required runtime control to be Evidenced (Implemented and Evidenced) or to carry an authorised, time-bounded compensating control (Compensating Control and Expiry / Review), before an Approved/Active agent shows OK; “Implemented” alone no longer passes (Playbook F.7.8; scenario finding W-01). The Agent Record AIR-ID check now uses the AI Register (AIG-INV-04) rule (AIR- plus four characters, warning), so IDs accepted by the Register are accepted here (T-10). Follow-up from the v3.9.2 re-test (NEW-01): a compensating control passes only while its Expiry / Review date is on or after today; an expired (or non-date) Expiry / Review shows “compensating control expired, re-authorise”. See QA change log.
A22: 0.5 working draft | B22: 1 October 2026 — v3.9.4: Field Guidance adds a line on log retention: record the retention period and its basis in Notes (column AD): the DPIA reference, or the records retention schedule class agreed with the records manager where there is no DPIA; in line with Playbook §4.7.12 and AIG-ASS-11 Section 4; no field, header, list or validation changed. Proposed — for Council confirmation.
A23: 0.6 working draft | B23: 4 October 2026 — v3.9.9: proportionate ASBOM. New column BL shows the record level each agent needs (Core; Core plus features; Full at T3 and above, with financial authority or while the tier is unassessed). The core record includes the Agency Profile row. Field Guidance lists the core fields and the sheets each feature switches on, and allows “Not disclosed by supplier” for supplier-side detail but never for a core field. Record QA checks the core fields and the level’s sheets before go-live; the Runtime Controls template no longer defaults all ten controls to Required (set per AIG-ASS-11). Proposed — for Council confirmation.
A24: 0.7 working draft | B24: 16 October 2026 — v3.9.11 / Playbook 19.9.23: new Platform Agent Inventory sheet for agents built on an approved platform (Playbook Appendix F.8), with lists PlatformAgentClass, PlatformAgentAudience and LGATier and a Field Guidance line. Its columns match the Multi-Board Triage tool’s platform agent screening download. No existing sheet, field, formula or validation changed. Proposed — for Council confirmation.

Sheet Agent Record
A1: Agent Record — one row per agent
A2: Keyed to the permanent AIR-ID. Agent authority is an envelope, not blanket approval of every UC-ID. Record authorised UC-ID scope and its delegated decision reference; action records must carry the UC-ID actually invoked.
A3: One agent per row. Every agent that can act needs at least the core record (the core columns are listed on Field Guidance). Column BL shows the level this agent needs: Core; Core plus features (persistence, memory, tool discovery or credential access, and delegation each switch on their own sheets); or Full at T3 and above, with financial authority or while the tier is unassessed (every sheet, including Capability Vector, Components, all ten Runtime Controls and the Authority Graph). “Not disclosed by supplier” is allowed for supplier-side detail, never for a core field. Fail safe: where autonomy, authority or containment is unclear, classify at the higher tier until assessed. | AY3: Stable, unique per-agent key; keep linked to parent AIR-ID. See INTEGRATION INV-04 DEC-04. | BJ3: Permitted autonomy is granted per UC-ID by the delegated decision (AIG-DEC-03), never inferred from the assessed level (QA-053).
A4: AIR-ID | B4: Agent Name | C4: Approved Purpose (mandate) | D4: Prohibited Purposes | E4: Decisions never delegated | F4: Max acceptable consequence | G4: Accountable Executive | H4: Business Owner | I4: Operator / Platform | J4: Environment (stage) | K4: Jurisdiction | L4: Assessed autonomy level (triage; not permission) | M4: Agency Tier | N4: AGPI Priority (from AIG-INV-04) | O4: Persistence? | P4: Memory Type | Q4: Can delegate? | R4: Financial Authority (limit) | S4: Permission Scope (summary) | T4: Identity / credential provenance | U4: Suspension mechanism | V4: Termination mechanism | W4: Kill-switch tested? | X4: Rollback capability? | Y4: Evaluation / red-team status | Z4: Date authorised | AA4: Authority expiry / next reauthorisation | AB4: Governance Approval Status | AC4: Operational Status | AD4: Notes | AE4: Memory Read Scope | AF4: Memory Write Scope | AG4: Memory Retention / Deletion | AH4: Memory Provenance | AI4: Memory Isolation / Poisoning Control | AJ4: Model Routing / Fallback | AK4: Frontier Model? | AL4: Max Delegation Depth | AM4: Recursion Allowed? | AN4: Max Concurrent Sub-agents | AO4: Runtime Control State | AP4: Containment Test Date | AQ4: Time to Containment | AR4: Action Record Available? | AS4: Human Oversight Mode | AT4: Reversibility Class | AU4: Compensating Action | AV4: Budget / Transaction Ceiling | AW4: Agent Creation Authority | AX4: Self-Modification Authority | AY4: AG-ID | AZ4: UC-ID(s) within this authority envelope (reference only) | BA4: Use-specific delegated decision / gate reference(s) | BB4: ASBOM record version | BC4: ASBOM version effective date | BD4: Exposure | BE4: Agency profile ref (Agency Profile sheet — the record) | BF4: Mandatory tier floor applied (trigger) | BG4: Governing pathway (higher of risk-tier pathway and agency-tier minimum) | BH4: Oversight mode rationale | BI4: Record QA | BJ4: Permitted autonomy level (granted at Gate 6) | BK4: Permitted autonomy decision ref (AIG-DEC-03) | BL4: Record level required (Core / Core plus features / Full)
A5: AIR-EXAMPLE | B5: Example — delete before use | C5: Draft supplier invoices for human approval | D5: Making payments; changing bank details | E5: Any payment release | F5: Material financial loss if wrong | G5: Director of Finance | H5: AP Team Lead | I5: AI platform | J5: Pre-production / test | K5: England | L5: A2 bounded execution | M5: T2 bounded agent | N5: Priority 3 | O5: No | P5: Context | Q5: No | R5: No | S5: Read AP mailbox; draft only | T5: Platform service identity AP-047 | U5: Disable tool + revoke token in console | V5: Delete service identity | W5: Yes | X5: Yes | Y5: Pre-deployment eval passed; red-team pending | Z5: 46280 | AA5: 46461 | AB5: Pending | AC5: Not live | AD5: Example row — delete before use. Kill-switch test 2026-09-10 recorded in Containment Test Date. | AE5: Required at Full level or where the feature applies — complete before production | AF5: Required at Full level or where the feature applies — complete before production | AG5: Required at Full level or where the feature applies — complete before production | AH5: Required at Full level or where the feature applies — complete before production | AI5: Required at Full level or where the feature applies — complete before production | AJ5: Required at Full level or where the feature applies — complete before production | AK5: No | AL5: Required at Full level or where the feature applies — complete before production | AM5: No | AN5: Required at Full level or where the feature applies — complete before production | AO5: Designed | AP5: 46275 | AQ5: Required at Full level or where the feature applies — complete before production | AR5: Required at Full level or where the feature applies — complete before production | AS5: Pre-action approval | AT5: Fully reversible | AU5: Required at Full level or where the feature applies — complete before production | AV5: Required at Full level or where the feature applies — complete before production | AW5: Required at Full level or where the feature applies — complete before production | AX5: Required at Full level or where the feature applies — complete before production | AY5: AG-EXAMPLE | AZ5: UC-EXAMPLE | BA5: AIG-DEC-03 reference (example) | BB5: 0.1 | BC5: 46280 | BD5: Internal | BE5: Agency Profile, AG-EXAMPLE | BF5: None triggered | BG5: Medium (risk-tier pathway Medium; T2 agency-tier minimum Medium): agentic controls review at Gate 2 | BH5: Drafts only; every payment-related action needs per-action human approval (D7). | BI5: =IF(A5="","",IF(AY5="","AG-ID missing",IF(COUNTIF($AY$5:$AY$203,AY5)>1,"Duplicate AG-ID",IF(AND(OR(AB5="Approved",AB5="Approved with conditions",AC5="Active"),OR(B5="",C5="",H5="",I5="",M5="",S5="",T5="",U5="",X5="",AA5="",AZ5="",BE5="")),"Core record incomplete: name, purpose, owner, platform, agency tier and profile ref, permission scope, credentials, how to stop it, how to undo it, UC-IDs and review date are needed before go-live",IF(AND(OR(AB5="Approved",AB5="Approved with conditions",AC5="Active"),COUNTIF('Agency Profile'!$B$5:$B$203,AY5)=0),"Agency Profile row missing: record the five agency scores behind the tier",IF(AND(OR(AB5="Approved",AB5="Approved with conditions",AC5="Active"),OR(B5="Not disclosed by supplier",C5="Not disclosed by supplier",H5="Not disclosed by supplier",I5="Not disclosed by supplier",M5="Not disclosed by supplier",S5="Not disclosed by supplier",T5="Not disclosed by supplier",U5="Not disclosed by supplier",X5="Not disclosed by supplier",AA5="Not disclosed by supplier",AZ5="Not disclosed by supplier",BE5="Not disclosed by supplier",AS5="Not disclosed by supplier",BJ5="Not disclosed by supplier")),"A core field says Not disclosed by supplier: the Council must answer the core fields itself",IF(AND(OR(AB5="Approved",AB5="Approved with conditions",AC5="Active"),BL5="Full",OR(COUNTIF('Capability Vector'!$B$5:$B$203,AY5)=0,COUNTIF(Components!$B$5:$B$303,AY5)=0,COUNTIFS('Runtime Controls'!$B$5:$B$303,AY5,'Runtime Controls'!$E$5:$E$303,"<>")<10)),"Full ASBOM (T3 and above, financial authority or tier not assessed): Capability Vector, Components and all ten Runtime Controls rows with Required State set are needed",IF(AND(OR(AB5="Approved",AB5="Approved with conditions",AC5="Active"),OR(Q5="Yes",BL5="Full"),COUNTIF('Authority & Delegations'!$C$5:$C$303,AY5)=0),"Delegation or Full level: add Authority & Delegations rows (they feed the Authority Graph)",IF(AND(OR(AB5="Approved",AB5="Approved with conditions",AC5="Active"),Q5="Yes",COUNTIF('Multi-Agent Controls'!$B$5:$B$303,AY5)=0),"Delegation: add a Multi-Agent Controls row",IF(AND(OR(AB5="Approved",AB5="Approved with conditions",AC5="Active"),O5="Yes",COUNTIF('Runtime Controls'!$B$5:$B$303,AY5)=0),"Persistence: add Runtime Controls rows for how it is stopped and contained",IF(AND(OR(AB5="Approved",AB5="Approved with conditions",AC5="Active"),OR(P5="Working memory",P5="Retrieved knowledge",P5="Persistent memory"),COUNTIF('Memory Controls'!$B$5:$B$303,AY5)=0),"Memory: add a Memory Controls row for each memory store",IF(AND(OR(AB5="Approved",AB5="Approved with conditions",AC5="Active"),COUNTIFS('Capability Vector'!$B$5:$B$203,AY5,'Capability Vector'!$P$5:$P$203,"Yes")+COUNTIFS('Capability Vector'!$B$5:$B$203,AY5,'Capability Vector'!$P$5:$P$203,"Scoped")+COUNTIFS('Capability Vector'!$B$5:$B$203,AY5,'Capability Vector'!$R$5:$R$203,"Yes")+COUNTIFS('Capability Vector'!$B$5:$B$203,AY5,'Capability Vector'!$R$5:$R$203,"Scoped")>0,OR(COUNTIF('Tool Authority Registry'!$B$5:$B$303,AY5)=0,COUNTIF('Interface Register'!$B$5:$B$303,AY5)=0)),"Tool discovery or credential access: add Tool Authority Registry and Interface Register rows",IF(AND(OR(AB5="Approved",AB5="Approved with conditions"),AC5="Active",COUNTIFS('Runtime Controls'!$B$5:$B$303,AY5,'Runtime Controls'!$E$5:$E$303,"Required",'Runtime Controls'!$F$5:$F$303,"<>Evidenced",'Runtime Controls'!$M$5:$M$303,"")+COUNTIFS('Runtime Controls'!$B$5:$B$303,AY5,'Runtime Controls'!$E$5:$E$303,"Required",'Runtime Controls'!$F$5:$F$303,"<>Evidenced",'Runtime Controls'!$M$5:$M$303,"<>",'Runtime Controls'!$L$5:$L$303,"")>0),"Production requirement (Gate 6): required control not Implemented and Evidenced, and no time-bounded compensating control (F.7.8)",IF(AND(OR(AB5="Approved",AB5="Approved with conditions"),AC5="Active",COUNTIFS('Runtime Controls'!$B$5:$B$303,AY5,'Runtime Controls'!$E$5:$E$303,"Required",'Runtime Controls'!$F$5:$F$303,"<>Evidenced",'Runtime Controls'!$M$5:$M$303,"<>",'Runtime Controls'!$L$5:$L$303,"<>")-COUNTIFS('Runtime Controls'!$B$5:$B$303,AY5,'Runtime Controls'!$E$5:$E$303,"Required",'Runtime Controls'!$F$5:$F$303,"<>Evidenced",'Runtime Controls'!$M$5:$M$303,"<>",'Runtime Controls'!$L$5:$L$303,">="&TODAY())>0),"Production requirement (Gate 6): compensating control expired, re-authorise (Expiry / Review must be a date on or after today; F.7.8)",IF(OR(AS5="",BB5=""),"Oversight mode or ASBOM version missing",IF(AND(AC5="Active",BA5=""),"Active without use-specific decision ref (F.7.8)",IF(AND(BJ5<>"",BK5=""),"Permitted autonomy decision ref missing",IF(AND(AC5="Active",BJ5=""),"Active without permitted autonomy level","OK")))))))))))))))))) | BJ5: A2 bounded execution | BK5: AIG-DEC-03 reference (example) | BL5: =IF(A5="","",IF(OR(M5="",LEFT(M5,2)="T3",LEFT(M5,2)="T4",LEFT(M5,2)="T5",AND(R5<>"",R5<>"No",R5<>"None",R5<>"0",R5<>"N/A")),"Full",IF(OR(O5="Yes",Q5="Yes",P5="Working memory",P5="Retrieved knowledge",P5="Persistent memory",COUNTIFS('Capability Vector'!$B$5:$B$203,AY5,'Capability Vector'!$P$5:$P$203,"Yes")+COUNTIFS('Capability Vector'!$B$5:$B$203,AY5,'Capability Vector'!$P$5:$P$203,"Scoped")+COUNTIFS('Capability Vector'!$B$5:$B$203,AY5,'Capability Vector'!$R$5:$R$203,"Yes")+COUNTIFS('Capability Vector'!$B$5:$B$203,AY5,'Capability Vector'!$R$5:$R$203,"Scoped")>0),"Core plus features","Core")))
BI6: =IF(A6="","",IF(AY6="","AG-ID missing",IF(COUNTIF($AY$5:$AY$203,AY6)>1,"Duplicate AG-ID",IF(AND(OR(AB6="Approved",AB6="Approved with conditions",AC6="Active"),OR(B6="",C6="",H6="",I6="",M6="",S6="",T6="",U6="",X6="",AA6="",AZ6="",BE6="")),"Core record incomplete: name, purpose, owner, platform, agency tier and profile ref, permission scope, credentials, how to stop it, how to undo it, UC-IDs and review date are needed before go-live",IF(AND(OR(AB6="Approved",AB6="Approved with conditions",AC6="Active"),COUNTIF('Agency Profile'!$B$5:$B$203,AY6)=0),"Agency Profile row missing: record the five agency scores behind the tier",IF(AND(OR(AB6="Approved",AB6="Approved with conditions",AC6="Active"),OR(B6="Not disclosed by supplier",C6="Not disclosed by supplier",H6="Not disclosed by supplier",I6="Not disclosed by supplier",M6="Not disclosed by supplier",S6="Not disclosed by supplier",T6="Not disclosed by supplier",U6="Not disclosed by supplier",X6="Not disclosed by supplier",AA6="Not disclosed by supplier",AZ6="Not disclosed by supplier",BE6="Not disclosed by supplier",AS6="Not disclosed by supplier",BJ6="Not disclosed by supplier")),"A core field says Not disclosed by supplier: the Council must answer the core fields itself",IF(AND(OR(AB6="Approved",AB6="Approved with conditions",AC6="Active"),BL6="Full",OR(COUNTIF('Capability Vector'!$B$5:$B$203,AY6)=0,COUNTIF(Components!$B$5:$B$303,AY6)=0,COUNTIFS('Runtime Controls'!$B$5:$B$303,AY6,'Runtime Controls'!$E$5:$E$303,"<>")<10)),"Full ASBOM (T3 and above, financial authority or tier not assessed): Capability Vector, Components and all ten Runtime Controls rows with Required State set are needed",IF(AND(OR(AB6="Approved",AB6="Approved with conditions",AC6="Active"),OR(Q6="Yes",BL6="Full"),COUNTIF('Authority & Delegations'!$C$5:$C$303,AY6)=0),"Delegation or Full level: add Authority & Delegations rows (they feed the Authority Graph)",IF(AND(OR(AB6="Approved",AB6="Approved with conditions",AC6="Active"),Q6="Yes",COUNTIF('Multi-Agent Controls'!$B$5:$B$303,AY6)=0),"Delegation: add a Multi-Agent Controls row",IF(AND(OR(AB6="Approved",AB6="Approved with conditions",AC6="Active"),O6="Yes",COUNTIF('Runtime Controls'!$B$5:$B$303,AY6)=0),"Persistence: add Runtime Controls rows for how it is stopped and contained",IF(AND(OR(AB6="Approved",AB6="Approved with conditions",AC6="Active"),OR(P6="Working memory",P6="Retrieved knowledge",P6="Persistent memory"),COUNTIF('Memory Controls'!$B$5:$B$303,AY6)=0),"Memory: add a Memory Controls row for each memory store",IF(AND(OR(AB6="Approved",AB6="Approved with conditions",AC6="Active"),COUNTIFS('Capability Vector'!$B$5:$B$203,AY6,'Capability Vector'!$P$5:$P$203,"Yes")+COUNTIFS('Capability Vector'!$B$5:$B$203,AY6,'Capability Vector'!$P$5:$P$203,"Scoped")+COUNTIFS('Capability Vector'!$B$5:$B$203,AY6,'Capability Vector'!$R$5:$R$203,"Yes")+COUNTIFS('Capability Vector'!$B$5:$B$203,AY6,'Capability Vector'!$R$5:$R$203,"Scoped")>0,OR(COUNTIF('Tool Authority Registry'!$B$5:$B$303,AY6)=0,COUNTIF('Interface Register'!$B$5:$B$303,AY6)=0)),"Tool discovery or credential access: add Tool Authority Registry and Interface Register rows",IF(AND(OR(AB6="Approved",AB6="Approved with conditions"),AC6="Active",COUNTIFS('Runtime Controls'!$B$5:$B$303,AY6,'Runtime Controls'!$E$5:$E$303,"Required",'Runtime Controls'!$F$5:$F$303,"<>Evidenced",'Runtime Controls'!$M$5:$M$303,"")+COUNTIFS('Runtime Controls'!$B$5:$B$303,AY6,'Runtime Controls'!$E$5:$E$303,"Required",'Runtime Controls'!$F$5:$F$303,"<>Evidenced",'Runtime Controls'!$M$5:$M$303,"<>",'Runtime Controls'!$L$5:$L$303,"")>0),"Production requirement (Gate 6): required control not Implemented and Evidenced, and no time-bounded compensating control (F.7.8)",IF(AND(OR(AB6="Approved",AB6="Approved with conditions"),AC6="Active",COUNTIFS('Runtime Controls'!$B$5:$B$303,AY6,'Runtime Controls'!$E$5:$E$303,"Required",'Runtime Controls'!$F$5:$F$303,"<>Evidenced",'Runtime Controls'!$M$5:$M$303,"<>",'Runtime Controls'!$L$5:$L$303,"<>")-COUNTIFS('Runtime Controls'!$B$5:$B$303,AY6,'Runtime Controls'!$E$5:$E$303,"Required",'Runtime Controls'!$F$5:$F$303,"<>Evidenced",'Runtime Controls'!$M$5:$M$303,"<>",'Runtime Controls'!$L$5:$L$303,">="&TODAY())>0),"Production requirement (Gate 6): compensating control expired, re-authorise (Expiry / Review must be a date on or after today; F.7.8)",IF(OR(AS6="",BB6=""),"Oversight mode or ASBOM version missing",IF(AND(AC6="Active",BA6=""),"Active without use-specific decision ref (F.7.8)",IF(AND(BJ6<>"",BK6=""),"Permitted autonomy decision ref missing",IF(AND(AC6="Active",BJ6=""),"Active without permitted autonomy level","OK")))))))))))))))))) | BL6: =IF(A6="","",IF(OR(M6="",LEFT(M6,2)="T3",LEFT(M6,2)="T4",LEFT(M6,2)="T5",AND(R6<>"",R6<>"No",R6<>"None",R6<>"0",R6<>"N/A")),"Full",IF(OR(O6="Yes",Q6="Yes",P6="Working memory",P6="Retrieved knowledge",P6="Persistent memory",COUNTIFS('Capability Vector'!$B$5:$B$203,AY6,'Capability Vector'!$P$5:$P$203,"Yes")+COUNTIFS('Capability Vector'!$B$5:$B$203,AY6,'Capability Vector'!$P$5:$P$203,"Scoped")+COUNTIFS('Capability Vector'!$B$5:$B$203,AY6,'Capability Vector'!$R$5:$R$203,"Yes")+COUNTIFS('Capability Vector'!$B$5:$B$203,AY6,'Capability Vector'!$R$5:$R$203,"Scoped")>0),"Core plus features","Core")))
BI7: =IF(A7="","",IF(AY7="","AG-ID missing",IF(COUNTIF($AY$5:$AY$203,AY7)>1,"Duplicate AG-ID",IF(AND(OR(AB7="Approved",AB7="Approved with conditions",AC7="Active"),OR(B7="",C7="",H7="",I7="",M7="",S7="",T7="",U7="",X7="",AA7="",AZ7="",BE7="")),"Core record incomplete: name, purpose, owner, platform, agency tier and profile ref, permission scope, credentials, how to stop it, how to undo it, UC-IDs and review date are needed before go-live",IF(AND(OR(AB7="Approved",AB7="Approved with conditions",AC7="Active"),COUNTIF('Agency Profile'!$B$5:$B$203,AY7)=0),"Agency Profile row missing: record the five agency scores behind the tier",IF(AND(OR(AB7="Approved",AB7="Approved with conditions",AC7="Active"),OR(B7="Not disclosed by supplier",C7="Not disclosed by supplier",H7="Not disclosed by supplier",I7="Not disclosed by supplier",M7="Not disclosed by supplier",S7="Not disclosed by supplier",T7="Not disclosed by supplier",U7="Not disclosed by supplier",X7="Not disclosed by supplier",AA7="Not disclosed by supplier",AZ7="Not disclosed by supplier",BE7="Not disclosed by supplier",AS7="Not disclosed by supplier",BJ7="Not disclosed by supplier")),"A core field says Not disclosed by supplier: the Council must answer the core fields itself",IF(AND(OR(AB7="Approved",AB7="Approved with conditions",AC7="Active"),BL7="Full",OR(COUNTIF('Capability Vector'!$B$5:$B$203,AY7)=0,COUNTIF(Components!$B$5:$B$303,AY7)=0,COUNTIFS('Runtime Controls'!$B$5:$B$303,AY7,'Runtime Controls'!$E$5:$E$303,"<>")<10)),"Full ASBOM (T3 and above, financial authority or tier not assessed): Capability Vector, Components and all ten Runtime Controls rows with Required State set are needed",IF(AND(OR(AB7="Approved",AB7="Approved with conditions",AC7="Active"),OR(Q7="Yes",BL7="Full"),COUNTIF('Authority & Delegations'!$C$5:$C$303,AY7)=0),"Delegation or Full level: add Authority & Delegations rows (they feed the Authority Graph)",IF(AND(OR(AB7="Approved",AB7="Approved with conditions",AC7="Active"),Q7="Yes",COUNTIF('Multi-Agent Controls'!$B$5:$B$303,AY7)=0),"Delegation: add a Multi-Agent Controls row",IF(AND(OR(AB7="Approved",AB7="Approved with conditions",AC7="Active"),O7="Yes",COUNTIF('Runtime Controls'!$B$5:$B$303,AY7)=0),"Persistence: add Runtime Controls rows for how it is stopped and contained",IF(AND(OR(AB7="Approved",AB7="Approved with conditions",AC7="Active"),OR(P7="Working memory",P7="Retrieved knowledge",P7="Persistent memory"),COUNTIF('Memory Controls'!$B$5:$B$303,AY7)=0),"Memory: add a Memory Controls row for each memory store",IF(AND(OR(AB7="Approved",AB7="Approved with conditions",AC7="Active"),COUNTIFS('Capability Vector'!$B$5:$B$203,AY7,'Capability Vector'!$P$5:$P$203,"Yes")+COUNTIFS('Capability Vector'!$B$5:$B$203,AY7,'Capability Vector'!$P$5:$P$203,"Scoped")+COUNTIFS('Capability Vector'!$B$5:$B$203,AY7,'Capability Vector'!$R$5:$R$203,"Yes")+COUNTIFS('Capability Vector'!$B$5:$B$203,AY7,'Capability Vector'!$R$5:$R$203,"Scoped")>0,OR(COUNTIF('Tool Authority Registry'!$B$5:$B$303,AY7)=0,COUNTIF('Interface Register'!$B$5:$B$303,AY7)=0)),"Tool discovery or credential access: add Tool Authority Registry and Interface Register rows",IF(AND(OR(AB7="Approved",AB7="Approved with conditions"),AC7="Active",COUNTIFS('Runtime Controls'!$B$5:$B$303,AY7,'Runtime Controls'!$E$5:$E$303,"Required",'Runtime Controls'!$F$5:$F$303,"<>Evidenced",'Runtime Controls'!$M$5:$M$303,"")+COUNTIFS('Runtime Controls'!$B$5:$B$303,AY7,'Runtime Controls'!$E$5:$E$303,"Required",'Runtime Controls'!$F$5:$F$303,"<>Evidenced",'Runtime Controls'!$M$5:$M$303,"<>",'Runtime Controls'!$L$5:$L$303,"")>0),"Production requirement (Gate 6): required control not Implemented and Evidenced, and no time-bounded compensating control (F.7.8)",IF(AND(OR(AB7="Approved",AB7="Approved with conditions"),AC7="Active",COUNTIFS('Runtime Controls'!$B$5:$B$303,AY7,'Runtime Controls'!$E$5:$E$303,"Required",'Runtime Controls'!$F$5:$F$303,"<>Evidenced",'Runtime Controls'!$M$5:$M$303,"<>",'Runtime Controls'!$L$5:$L$303,"<>")-COUNTIFS('Runtime Controls'!$B$5:$B$303,AY7,'Runtime Controls'!$E$5:$E$303,"Required",'Runtime Controls'!$F$5:$F$303,"<>Evidenced",'Runtime Controls'!$M$5:$M$303,"<>",'Runtime Controls'!$L$5:$L$303,">="&TODAY())>0),"Production requirement (Gate 6): compensating control expired, re-authorise (Expiry / Review must be a date on or after today; F.7.8)",IF(OR(AS7="",BB7=""),"Oversight mode or ASBOM version missing",IF(AND(AC7="Active",BA7=""),"Active without use-specific decision ref (F.7.8)",IF(AND(BJ7<>"",BK7=""),"Permitted autonomy decision ref missing",IF(AND(AC7="Active",BJ7=""),"Active without permitted autonomy level","OK")))))))))))))))))) | BL7: =IF(A7="","",IF(OR(M7="",LEFT(M7,2)="T3",LEFT(M7,2)="T4",LEFT(M7,2)="T5",AND(R7<>"",R7<>"No",R7<>"None",R7<>"0",R7<>"N/A")),"Full",IF(OR(O7="Yes",Q7="Yes",P7="Working memory",P7="Retrieved knowledge",P7="Persistent memory",COUNTIFS('Capability Vector'!$B$5:$B$203,AY7,'Capability Vector'!$P$5:$P$203,"Yes")+COUNTIFS('Capability Vector'!$B$5:$B$203,AY7,'Capability Vector'!$P$5:$P$203,"Scoped")+COUNTIFS('Capability Vector'!$B$5:$B$203,AY7,'Capability Vector'!$R$5:$R$203,"Yes")+COUNTIFS('Capability Vector'!$B$5:$B$203,AY7,'Capability Vector'!$R$5:$R$203,"Scoped")>0),"Core plus features","Core")))
BI8: =IF(A8="","",IF(AY8="","AG-ID missing",IF(COUNTIF($AY$5:$AY$203,AY8)>1,"Duplicate AG-ID",IF(AND(OR(AB8="Approved",AB8="Approved with conditions",AC8="Active"),OR(B8="",C8="",H8="",I8="",M8="",S8="",T8="",U8="",X8="",AA8="",AZ8="",BE8="")),"Core record incomplete: name, purpose, owner, platform, agency tier and profile ref, permission scope, credentials, how to stop it, how to undo it, UC-IDs and review date are needed before go-live",IF(AND(OR(AB8="Approved",AB8="Approved with conditions",AC8="Active"),COUNTIF('Agency Profile'!$B$5:$B$203,AY8)=0),"Agency Profile row missing: record the five agency scores behind the tier",IF(AND(OR(AB8="Approved",AB8="Approved with conditions",AC8="Active"),OR(B8="Not disclosed by supplier",C8="Not disclosed by supplier",H8="Not disclosed by supplier",I8="Not disclosed by supplier",M8="Not disclosed by supplier",S8="Not disclosed by supplier",T8="Not disclosed by supplier",U8="Not disclosed by supplier",X8="Not disclosed by supplier",AA8="Not disclosed by supplier",AZ8="Not disclosed by supplier",BE8="Not disclosed by supplier",AS8="Not disclosed by supplier",BJ8="Not disclosed by supplier")),"A core field says Not disclosed by supplier: the Council must answer the core fields itself",IF(AND(OR(AB8="Approved",AB8="Approved with conditions",AC8="Active"),BL8="Full",OR(COUNTIF('Capability Vector'!$B$5:$B$203,AY8)=0,COUNTIF(Components!$B$5:$B$303,AY8)=0,COUNTIFS('Runtime Controls'!$B$5:$B$303,AY8,'Runtime Controls'!$E$5:$E$303,"<>")<10)),"Full ASBOM (T3 and above, financial authority or tier not assessed): Capability Vector, Components and all ten Runtime Controls rows with Required State set are needed",IF(AND(OR(AB8="Approved",AB8="Approved with conditions",AC8="Active"),OR(Q8="Yes",BL8="Full"),COUNTIF('Authority & Delegations'!$C$5:$C$303,AY8)=0),"Delegation or Full level: add Authority & Delegations rows (they feed the Authority Graph)",IF(AND(OR(AB8="Approved",AB8="Approved with conditions",AC8="Active"),Q8="Yes",COUNTIF('Multi-Agent Controls'!$B$5:$B$303,AY8)=0),"Delegation: add a Multi-Agent Controls row",IF(AND(OR(AB8="Approved",AB8="Approved with conditions",AC8="Active"),O8="Yes",COUNTIF('Runtime Controls'!$B$5:$B$303,AY8)=0),"Persistence: add Runtime Controls rows for how it is stopped and contained",IF(AND(OR(AB8="Approved",AB8="Approved with conditions",AC8="Active"),OR(P8="Working memory",P8="Retrieved knowledge",P8="Persistent memory"),COUNTIF('Memory Controls'!$B$5:$B$303,AY8)=0),"Memory: add a Memory Controls row for each memory store",IF(AND(OR(AB8="Approved",AB8="Approved with conditions",AC8="Active"),COUNTIFS('Capability Vector'!$B$5:$B$203,AY8,'Capability Vector'!$P$5:$P$203,"Yes")+COUNTIFS('Capability Vector'!$B$5:$B$203,AY8,'Capability Vector'!$P$5:$P$203,"Scoped")+COUNTIFS('Capability Vector'!$B$5:$B$203,AY8,'Capability Vector'!$R$5:$R$203,"Yes")+COUNTIFS('Capability Vector'!$B$5:$B$203,AY8,'Capability Vector'!$R$5:$R$203,"Scoped")>0,OR(COUNTIF('Tool Authority Registry'!$B$5:$B$303,AY8)=0,COUNTIF('Interface Register'!$B$5:$B$303,AY8)=0)),"Tool discovery or credential access: add Tool Authority Registry and Interface Register rows",IF(AND(OR(AB8="Approved",AB8="Approved with conditions"),AC8="Active",COUNTIFS('Runtime Controls'!$B$5:$B$303,AY8,'Runtime Controls'!$E$5:$E$303,"Required",'Runtime Controls'!$F$5:$F$303,"<>Evidenced",'Runtime Controls'!$M$5:$M$303,"")+COUNTIFS('Runtime Controls'!$B$5:$B$303,AY8,'Runtime Controls'!$E$5:$E$303,"Required",'Runtime Controls'!$F$5:$F$303,"<>Evidenced",'Runtime Controls'!$M$5:$M$303,"<>",'Runtime Controls'!$L$5:$L$303,"")>0),"Production requirement (Gate 6): required control not Implemented and Evidenced, and no time-bounded compensating control (F.7.8)",IF(AND(OR(AB8="Approved",AB8="Approved with conditions"),AC8="Active",COUNTIFS('Runtime Controls'!$B$5:$B$303,AY8,'Runtime Controls'!$E$5:$E$303,"Required",'Runtime Controls'!$F$5:$F$303,"<>Evidenced",'Runtime Controls'!$M$5:$M$303,"<>",'Runtime Controls'!$L$5:$L$303,"<>")-COUNTIFS('Runtime Controls'!$B$5:$B$303,AY8,'Runtime Controls'!$E$5:$E$303,"Required",'Runtime Controls'!$F$5:$F$303,"<>Evidenced",'Runtime Controls'!$M$5:$M$303,"<>",'Runtime Controls'!$L$5:$L$303,">="&TODAY())>0),"Production requirement (Gate 6): compensating control expired, re-authorise (Expiry / Review must be a date on or after today; F.7.8)",IF(OR(AS8="",BB8=""),"Oversight mode or ASBOM version missing",IF(AND(AC8="Active",BA8=""),"Active without use-specific decision ref (F.7.8)",IF(AND(BJ8<>"",BK8=""),"Permitted autonomy decision ref missing",IF(AND(AC8="Active",BJ8=""),"Active without permitted autonomy level","OK")))))))))))))))))) | BL8: =IF(A8="","",IF(OR(M8="",LEFT(M8,2)="T3",LEFT(M8,2)="T4",LEFT(M8,2)="T5",AND(R8<>"",R8<>"No",R8<>"None",R8<>"0",R8<>"N/A")),"Full",IF(OR(O8="Yes",Q8="Yes",P8="Working memory",P8="Retrieved knowledge",P8="Persistent memory",COUNTIFS('Capability Vector'!$B$5:$B$203,AY8,'Capability Vector'!$P$5:$P$203,"Yes")+COUNTIFS('Capability Vector'!$B$5:$B$203,AY8,'Capability Vector'!$P$5:$P$203,"Scoped")+COUNTIFS('Capability Vector'!$B$5:$B$203,AY8,'Capability Vector'!$R$5:$R$203,"Yes")+COUNTIFS('Capability Vector'!$B$5:$B$203,AY8,'Capability Vector'!$R$5:$R$203,"Scoped")>0),"Core plus features","Core")))
BI9: =IF(A9="","",IF(AY9="","AG-ID missing",IF(COUNTIF($AY$5:$AY$203,AY9)>1,"Duplicate AG-ID",IF(AND(OR(AB9="Approved",AB9="Approved with conditions",AC9="Active"),OR(B9="",C9="",H9="",I9="",M9="",S9="",T9="",U9="",X9="",AA9="",AZ9="",BE9="")),"Core record incomplete: name, purpose, owner, platform, agency tier and profile ref, permission scope, credentials, how to stop it, how to undo it, UC-IDs and review date are needed before go-live",IF(AND(OR(AB9="Approved",AB9="Approved with conditions",AC9="Active"),COUNTIF('Agency Profile'!$B$5:$B$203,AY9)=0),"Agency Profile row missing: record the five agency scores behind the tier",IF(AND(OR(AB9="Approved",AB9="Approved with conditions",AC9="Active"),OR(B9="Not disclosed by supplier",C9="Not disclosed by supplier",H9="Not disclosed by supplier",I9="Not disclosed by supplier",M9="Not disclosed by supplier",S9="Not disclosed by supplier",T9="Not disclosed by supplier",U9="Not disclosed by supplier",X9="Not disclosed by supplier",AA9="Not disclosed by supplier",AZ9="Not disclosed by supplier",BE9="Not disclosed by supplier",AS9="Not disclosed by supplier",BJ9="Not disclosed by supplier")),"A core field says Not disclosed by supplier: the Council must answer the core fields itself",IF(AND(OR(AB9="Approved",AB9="Approved with conditions",AC9="Active"),BL9="Full",OR(COUNTIF('Capability Vector'!$B$5:$B$203,AY9)=0,COUNTIF(Components!$B$5:$B$303,AY9)=0,COUNTIFS('Runtime Controls'!$B$5:$B$303,AY9,'Runtime Controls'!$E$5:$E$303,"<>")<10)),"Full ASBOM (T3 and above, financial authority or tier not assessed): Capability Vector, Components and all ten Runtime Controls rows with Required State set are needed",IF(AND(OR(AB9="Approved",AB9="Approved with conditions",AC9="Active"),OR(Q9="Yes",BL9="Full"),COUNTIF('Authority & Delegations'!$C$5:$C$303,AY9)=0),"Delegation or Full level: add Authority & Delegations rows (they feed the Authority Graph)",IF(AND(OR(AB9="Approved",AB9="Approved with conditions",AC9="Active"),Q9="Yes",COUNTIF('Multi-Agent Controls'!$B$5:$B$303,AY9)=0),"Delegation: add a Multi-Agent Controls row",IF(AND(OR(AB9="Approved",AB9="Approved with conditions",AC9="Active"),O9="Yes",COUNTIF('Runtime Controls'!$B$5:$B$303,AY9)=0),"Persistence: add Runtime Controls rows for how it is stopped and contained",IF(AND(OR(AB9="Approved",AB9="Approved with conditions",AC9="Active"),OR(P9="Working memory",P9="Retrieved knowledge",P9="Persistent memory"),COUNTIF('Memory Controls'!$B$5:$B$303,AY9)=0),"Memory: add a Memory Controls row for each memory store",IF(AND(OR(AB9="Approved",AB9="Approved with conditions",AC9="Active"),COUNTIFS('Capability Vector'!$B$5:$B$203,AY9,'Capability Vector'!$P$5:$P$203,"Yes")+COUNTIFS('Capability Vector'!$B$5:$B$203,AY9,'Capability Vector'!$P$5:$P$203,"Scoped")+COUNTIFS('Capability Vector'!$B$5:$B$203,AY9,'Capability Vector'!$R$5:$R$203,"Yes")+COUNTIFS('Capability Vector'!$B$5:$B$203,AY9,'Capability Vector'!$R$5:$R$203,"Scoped")>0,OR(COUNTIF('Tool Authority Registry'!$B$5:$B$303,AY9)=0,COUNTIF('Interface Register'!$B$5:$B$303,AY9)=0)),"Tool discovery or credential access: add Tool Authority Registry and Interface Register rows",IF(AND(OR(AB9="Approved",AB9="Approved with conditions"),AC9="Active",COUNTIFS('Runtime Controls'!$B$5:$B$303,AY9,'Runtime Controls'!$E$5:$E$303,"Required",'Runtime Controls'!$F$5:$F$303,"<>Evidenced",'Runtime Controls'!$M$5:$M$303,"")+COUNTIFS('Runtime Controls'!$B$5:$B$303,AY9,'Runtime Controls'!$E$5:$E$303,"Required",'Runtime Controls'!$F$5:$F$303,"<>Evidenced",'Runtime Controls'!$M$5:$M$303,"<>",'Runtime Controls'!$L$5:$L$303,"")>0),"Production requirement (Gate 6): required control not Implemented and Evidenced, and no time-bounded compensating control (F.7.8)",IF(AND(OR(AB9="Approved",AB9="Approved with conditions"),AC9="Active",COUNTIFS('Runtime Controls'!$B$5:$B$303,AY9,'Runtime Controls'!$E$5:$E$303,"Required",'Runtime Controls'!$F$5:$F$303,"<>Evidenced",'Runtime Controls'!$M$5:$M$303,"<>",'Runtime Controls'!$L$5:$L$303,"<>")-COUNTIFS('Runtime Controls'!$B$5:$B$303,AY9,'Runtime Controls'!$E$5:$E$303,"Required",'Runtime Controls'!$F$5:$F$303,"<>Evidenced",'Runtime Controls'!$M$5:$M$303,"<>",'Runtime Controls'!$L$5:$L$303,">="&TODAY())>0),"Production requirement (Gate 6): compensating control expired, re-authorise (Expiry / Review must be a date on or after today; F.7.8)",IF(OR(AS9="",BB9=""),"Oversight mode or ASBOM version missing",IF(AND(AC9="Active",BA9=""),"Active without use-specific decision ref (F.7.8)",IF(AND(BJ9<>"",BK9=""),"Permitted autonomy decision ref missing",IF(AND(AC9="Active",BJ9=""),"Active without permitted autonomy level","OK")))))))))))))))))) | BL9: =IF(A9="","",IF(OR(M9="",LEFT(M9,2)="T3",LEFT(M9,2)="T4",LEFT(M9,2)="T5",AND(R9<>"",R9<>"No",R9<>"None",R9<>"0",R9<>"N/A")),"Full",IF(OR(O9="Yes",Q9="Yes",P9="Working memory",P9="Retrieved knowledge",P9="Persistent memory",COUNTIFS('Capability Vector'!$B$5:$B$203,AY9,'Capability Vector'!$P$5:$P$203,"Yes")+COUNTIFS('Capability Vector'!$B$5:$B$203,AY9,'Capability Vector'!$P$5:$P$203,"Scoped")+COUNTIFS('Capability Vector'!$B$5:$B$203,AY9,'Capability Vector'!$R$5:$R$203,"Yes")+COUNTIFS('Capability Vector'!$B$5:$B$203,AY9,'Capability Vector'!$R$5:$R$203,"Scoped")>0),"Core plus features","Core")))
BI10: =IF(A10="","",IF(AY10="","AG-ID missing",IF(COUNTIF($AY$5:$AY$203,AY10)>1,"Duplicate AG-ID",IF(AND(OR(AB10="Approved",AB10="Approved with conditions",AC10="Active"),OR(B10="",C10="",H10="",I10="",M10="",S10="",T10="",U10="",X10="",AA10="",AZ10="",BE10="")),"Core record incomplete: name, purpose, owner, platform, agency tier and profile ref, permission scope, credentials, how to stop it, how to undo it, UC-IDs and review date are needed before go-live",IF(AND(OR(AB10="Approved",AB10="Approved with conditions",AC10="Active"),COUNTIF('Agency Profile'!$B$5:$B$203,AY10)=0),"Agency Profile row missing: record the five agency scores behind the tier",IF(AND(OR(AB10="Approved",AB10="Approved with conditions",AC10="Active"),OR(B10="Not disclosed by supplier",C10="Not disclosed by supplier",H10="Not disclosed by supplier",I10="Not disclosed by supplier",M10="Not disclosed by supplier",S10="Not disclosed by supplier",T10="Not disclosed by supplier",U10="Not disclosed by supplier",X10="Not disclosed by supplier",AA10="Not disclosed by supplier",AZ10="Not disclosed by supplier",BE10="Not disclosed by supplier",AS10="Not disclosed by supplier",BJ10="Not disclosed by supplier")),"A core field says Not disclosed by supplier: the Council must answer the core fields itself",IF(AND(OR(AB10="Approved",AB10="Approved with conditions",AC10="Active"),BL10="Full",OR(COUNTIF('Capability Vector'!$B$5:$B$203,AY10)=0,COUNTIF(Components!$B$5:$B$303,AY10)=0,COUNTIFS('Runtime Controls'!$B$5:$B$303,AY10,'Runtime Controls'!$E$5:$E$303,"<>")<10)),"Full ASBOM (T3 and above, financial authority or tier not assessed): Capability Vector, Components and all ten Runtime Controls rows with Required State set are needed",IF(AND(OR(AB10="Approved",AB10="Approved with conditions",AC10="Active"),OR(Q10="Yes",BL10="Full"),COUNTIF('Authority & Delegations'!$C$5:$C$303,AY10)=0),"Delegation or Full level: add Authority & Delegations rows (they feed the Authority Graph)",IF(AND(OR(AB10="Approved",AB10="Approved with conditions",AC10="Active"),Q10="Yes",COUNTIF('Multi-Agent Controls'!$B$5:$B$303,AY10)=0),"Delegation: add a Multi-Agent Controls row",IF(AND(OR(AB10="Approved",AB10="Approved with conditions",AC10="Active"),O10="Yes",COUNTIF('Runtime Controls'!$B$5:$B$303,AY10)=0),"Persistence: add Runtime Controls rows for how it is stopped and contained",IF(AND(OR(AB10="Approved",AB10="Approved with conditions",AC10="Active"),OR(P10="Working memory",P10="Retrieved knowledge",P10="Persistent memory"),COUNTIF('Memory Controls'!$B$5:$B$303,AY10)=0),"Memory: add a Memory Controls row for each memory store",IF(AND(OR(AB10="Approved",AB10="Approved with conditions",AC10="Active"),COUNTIFS('Capability Vector'!$B$5:$B$203,AY10,'Capability Vector'!$P$5:$P$203,"Yes")+COUNTIFS('Capability Vector'!$B$5:$B$203,AY10,'Capability Vector'!$P$5:$P$203,"Scoped")+COUNTIFS('Capability Vector'!$B$5:$B$203,AY10,'Capability Vector'!$R$5:$R$203,"Yes")+COUNTIFS('Capability Vector'!$B$5:$B$203,AY10,'Capability Vector'!$R$5:$R$203,"Scoped")>0,OR(COUNTIF('Tool Authority Registry'!$B$5:$B$303,AY10)=0,COUNTIF('Interface Register'!$B$5:$B$303,AY10)=0)),"Tool discovery or credential access: add Tool Authority Registry and Interface Register rows",IF(AND(OR(AB10="Approved",AB10="Approved with conditions"),AC10="Active",COUNTIFS('Runtime Controls'!$B$5:$B$303,AY10,'Runtime Controls'!$E$5:$E$303,"Required",'Runtime Controls'!$F$5:$F$303,"<>Evidenced",'Runtime Controls'!$M$5:$M$303,"")+COUNTIFS('Runtime Controls'!$B$5:$B$303,AY10,'Runtime Controls'!$E$5:$E$303,"Required",'Runtime Controls'!$F$5:$F$303,"<>Evidenced",'Runtime Controls'!$M$5:$M$303,"<>",'Runtime Controls'!$L$5:$L$303,"")>0),"Production requirement (Gate 6): required control not Implemented and Evidenced, and no time-bounded compensating control (F.7.8)",IF(AND(OR(AB10="Approved",AB10="Approved with conditions"),AC10="Active",COUNTIFS('Runtime Controls'!$B$5:$B$303,AY10,'Runtime Controls'!$E$5:$E$303,"Required",'Runtime Controls'!$F$5:$F$303,"<>Evidenced",'Runtime Controls'!$M$5:$M$303,"<>",'Runtime Controls'!$L$5:$L$303,"<>")-COUNTIFS('Runtime Controls'!$B$5:$B$303,AY10,'Runtime Controls'!$E$5:$E$303,"Required",'Runtime Controls'!$F$5:$F$303,"<>Evidenced",'Runtime Controls'!$M$5:$M$303,"<>",'Runtime Controls'!$L$5:$L$303,">="&TODAY())>0),"Production requirement (Gate 6): compensating control expired, re-authorise (Expiry / Review must be a date on or after today; F.7.8)",IF(OR(AS10="",BB10=""),"Oversight mode or ASBOM version missing",IF(AND(AC10="Active",BA10=""),"Active without use-specific decision ref (F.7.8)",IF(AND(BJ10<>"",BK10=""),"Permitted autonomy decision ref missing",IF(AND(AC10="Active",BJ10=""),"Active without permitted autonomy level","OK")))))))))))))))))) | BL10: =IF(A10="","",IF(OR(M10="",LEFT(M10,2)="T3",LEFT(M10,2)="T4",LEFT(M10,2)="T5",AND(R10<>"",R10<>"No",R10<>"None",R10<>"0",R10<>"N/A")),"Full",IF(OR(O10="Yes",Q10="Yes",P10="Working memory",P10="Retrieved knowledge",P10="Persistent memory",COUNTIFS('Capability Vector'!$B$5:$B$203,AY10,'Capability Vector'!$P$5:$P$203,"Yes")+COUNTIFS('Capability Vector'!$B$5:$B$203,AY10,'Capability Vector'!$P$5:$P$203,"Scoped")+COUNTIFS('Capability Vector'!$B$5:$B$203,AY10,'Capability Vector'!$R$5:$R$203,"Yes")+COUNTIFS('Capability Vector'!$B$5:$B$203,AY10,'Capability Vector'!$R$5:$R$203,"Scoped")>0),"Core plus features","Core")))
BI11: =IF(A11="","",IF(AY11="","AG-ID missing",IF(COUNTIF($AY$5:$AY$203,AY11)>1,"Duplicate AG-ID",IF(AND(OR(AB11="Approved",AB11="Approved with conditions",AC11="Active"),OR(B11="",C11="",H11="",I11="",M11="",S11="",T11="",U11="",X11="",AA11="",AZ11="",BE11="")),"Core record incomplete: name, purpose, owner, platform, agency tier and profile ref, permission scope, credentials, how to stop it, how to undo it, UC-IDs and review date are needed before go-live",IF(AND(OR(AB11="Approved",AB11="Approved with conditions",AC11="Active"),COUNTIF('Agency Profile'!$B$5:$B$203,AY11)=0),"Agency Profile row missing: record the five agency scores behind the tier",IF(AND(OR(AB11="Approved",AB11="Approved with conditions",AC11="Active"),OR(B11="Not disclosed by supplier",C11="Not disclosed by supplier",H11="Not disclosed by supplier",I11="Not disclosed by supplier",M11="Not disclosed by supplier",S11="Not disclosed by supplier",T11="Not disclosed by supplier",U11="Not disclosed by supplier",X11="Not disclosed by supplier",AA11="Not disclosed by supplier",AZ11="Not disclosed by supplier",BE11="Not disclosed by supplier",AS11="Not disclosed by supplier",BJ11="Not disclosed by supplier")),"A core field says Not disclosed by supplier: the Council must answer the core fields itself",IF(AND(OR(AB11="Approved",AB11="Approved with conditions",AC11="Active"),BL11="Full",OR(COUNTIF('Capability Vector'!$B$5:$B$203,AY11)=0,COUNTIF(Components!$B$5:$B$303,AY11)=0,COUNTIFS('Runtime Controls'!$B$5:$B$303,AY11,'Runtime Controls'!$E$5:$E$303,"<>")<10)),"Full ASBOM (T3 and above, financial authority or tier not assessed): Capability Vector, Components and all ten Runtime Controls rows with Required State set are needed",IF(AND(OR(AB11="Approved",AB11="Approved with conditions",AC11="Active"),OR(Q11="Yes",BL11="Full"),COUNTIF('Authority & Delegations'!$C$5:$C$303,AY11)=0),"Delegation or Full level: add Authority & Delegations rows (they feed the Authority Graph)",IF(AND(OR(AB11="Approved",AB11="Approved with conditions",AC11="Active"),Q11="Yes",COUNTIF('Multi-Agent Controls'!$B$5:$B$303,AY11)=0),"Delegation: add a Multi-Agent Controls row",IF(AND(OR(AB11="Approved",AB11="Approved with conditions",AC11="Active"),O11="Yes",COUNTIF('Runtime Controls'!$B$5:$B$303,AY11)=0),"Persistence: add Runtime Controls rows for how it is stopped and contained",IF(AND(OR(AB11="Approved",AB11="Approved with conditions",AC11="Active"),OR(P11="Working memory",P11="Retrieved knowledge",P11="Persistent memory"),COUNTIF('Memory Controls'!$B$5:$B$303,AY11)=0),"Memory: add a Memory Controls row for each memory store",IF(AND(OR(AB11="Approved",AB11="Approved with conditions",AC11="Active"),COUNTIFS('Capability Vector'!$B$5:$B$203,AY11,'Capability Vector'!$P$5:$P$203,"Yes")+COUNTIFS('Capability Vector'!$B$5:$B$203,AY11,'Capability Vector'!$P$5:$P$203,"Scoped")+COUNTIFS('Capability Vector'!$B$5:$B$203,AY11,'Capability Vector'!$R$5:$R$203,"Yes")+COUNTIFS('Capability Vector'!$B$5:$B$203,AY11,'Capability Vector'!$R$5:$R$203,"Scoped")>0,OR(COUNTIF('Tool Authority Registry'!$B$5:$B$303,AY11)=0,COUNTIF('Interface Register'!$B$5:$B$303,AY11)=0)),"Tool discovery or credential access: add Tool Authority Registry and Interface Register rows",IF(AND(OR(AB11="Approved",AB11="Approved with conditions"),AC11="Active",COUNTIFS('Runtime Controls'!$B$5:$B$303,AY11,'Runtime Controls'!$E$5:$E$303,"Required",'Runtime Controls'!$F$5:$F$303,"<>Evidenced",'Runtime Controls'!$M$5:$M$303,"")+COUNTIFS('Runtime Controls'!$B$5:$B$303,AY11,'Runtime Controls'!$E$5:$E$303,"Required",'Runtime Controls'!$F$5:$F$303,"<>Evidenced",'Runtime Controls'!$M$5:$M$303,"<>",'Runtime Controls'!$L$5:$L$303,"")>0),"Production requirement (Gate 6): required control not Implemented and Evidenced, and no time-bounded compensating control (F.7.8)",IF(AND(OR(AB11="Approved",AB11="Approved with conditions"),AC11="Active",COUNTIFS('Runtime Controls'!$B$5:$B$303,AY11,'Runtime Controls'!$E$5:$E$303,"Required",'Runtime Controls'!$F$5:$F$303,"<>Evidenced",'Runtime Controls'!$M$5:$M$303,"<>",'Runtime Controls'!$L$5:$L$303,"<>")-COUNTIFS('Runtime Controls'!$B$5:$B$303,AY11,'Runtime Controls'!$E$5:$E$303,"Required",'Runtime Controls'!$F$5:$F$303,"<>Evidenced",'Runtime Controls'!$M$5:$M$303,"<>",'Runtime Controls'!$L$5:$L$303,">="&TODAY())>0),"Production requirement (Gate 6): compensating control expired, re-authorise (Expiry / Review must be a date on or after today; F.7.8)",IF(OR(AS11="",BB11=""),"Oversight mode or ASBOM version missing",IF(AND(AC11="Active",BA11=""),"Active without use-specific decision ref (F.7.8)",IF(AND(BJ11<>"",BK11=""),"Permitted autonomy decision ref missing",IF(AND(AC11="Active",BJ11=""),"Active without permitted autonomy level","OK")))))))))))))))))) | BL11: =IF(A11="","",IF(OR(M11="",LEFT(M11,2)="T3",LEFT(M11,2)="T4",LEFT(M11,2)="T5",AND(R11<>"",R11<>"No",R11<>"None",R11<>"0",R11<>"N/A")),"Full",IF(OR(O11="Yes",Q11="Yes",P11="Working memory",P11="Retrieved knowledge",P11="Persistent memory",COUNTIFS('Capability Vector'!$B$5:$B$203,AY11,'Capability Vector'!$P$5:$P$203,"Yes")+COUNTIFS('Capability Vector'!$B$5:$B$203,AY11,'Capability Vector'!$P$5:$P$203,"Scoped")+COUNTIFS('Capability Vector'!$B$5:$B$203,AY11,'Capability Vector'!$R$5:$R$203,"Yes")+COUNTIFS('Capability Vector'!$B$5:$B$203,AY11,'Capability Vector'!$R$5:$R$203,"Scoped")>0),"Core plus features","Core")))
BI12: =IF(A12="","",IF(AY12="","AG-ID missing",IF(COUNTIF($AY$5:$AY$203,AY12)>1,"Duplicate AG-ID",IF(AND(OR(AB12="Approved",AB12="Approved with conditions",AC12="Active"),OR(B12="",C12="",H12="",I12="",M12="",S12="",T12="",U12="",X12="",AA12="",AZ12="",BE12="")),"Core record incomplete: name, purpose, owner, platform, agency tier and profile ref, permission scope, credentials, how to stop it, how to undo it, UC-IDs and review date are needed before go-live",IF(AND(OR(AB12="Approved",AB12="Approved with conditions",AC12="Active"),COUNTIF('Agency Profile'!$B$5:$B$203,AY12)=0),"Agency Profile row missing: record the five agency scores behind the tier",IF(AND(OR(AB12="Approved",AB12="Approved with conditions",AC12="Active"),OR(B12="Not disclosed by supplier",C12="Not disclosed by supplier",H12="Not disclosed by supplier",I12="Not disclosed by supplier",M12="Not disclosed by supplier",S12="Not disclosed by supplier",T12="Not disclosed by supplier",U12="Not disclosed by supplier",X12="Not disclosed by supplier",AA12="Not disclosed by supplier",AZ12="Not disclosed by supplier",BE12="Not disclosed by supplier",AS12="Not disclosed by supplier",BJ12="Not disclosed by supplier")),"A core field says Not disclosed by supplier: the Council must answer the core fields itself",IF(AND(OR(AB12="Approved",AB12="Approved with conditions",AC12="Active"),BL12="Full",OR(COUNTIF('Capability Vector'!$B$5:$B$203,AY12)=0,COUNTIF(Components!$B$5:$B$303,AY12)=0,COUNTIFS('Runtime Controls'!$B$5:$B$303,AY12,'Runtime Controls'!$E$5:$E$303,"<>")<10)),"Full ASBOM (T3 and above, financial authority or tier not assessed): Capability Vector, Components and all ten Runtime Controls rows with Required State set are needed",IF(AND(OR(AB12="Approved",AB12="Approved with conditions",AC12="Active"),OR(Q12="Yes",BL12="Full"),COUNTIF('Authority & Delegations'!$C$5:$C$303,AY12)=0),"Delegation or Full level: add Authority & Delegations rows (they feed the Authority Graph)",IF(AND(OR(AB12="Approved",AB12="Approved with conditions",AC12="Active"),Q12="Yes",COUNTIF('Multi-Agent Controls'!$B$5:$B$303,AY12)=0),"Delegation: add a Multi-Agent Controls row",IF(AND(OR(AB12="Approved",AB12="Approved with conditions",AC12="Active"),O12="Yes",COUNTIF('Runtime Controls'!$B$5:$B$303,AY12)=0),"Persistence: add Runtime Controls rows for how it is stopped and contained",IF(AND(OR(AB12="Approved",AB12="Approved with conditions",AC12="Active"),OR(P12="Working memory",P12="Retrieved knowledge",P12="Persistent memory"),COUNTIF('Memory Controls'!$B$5:$B$303,AY12)=0),"Memory: add a Memory Controls row for each memory store",IF(AND(OR(AB12="Approved",AB12="Approved with conditions",AC12="Active"),COUNTIFS('Capability Vector'!$B$5:$B$203,AY12,'Capability Vector'!$P$5:$P$203,"Yes")+COUNTIFS('Capability Vector'!$B$5:$B$203,AY12,'Capability Vector'!$P$5:$P$203,"Scoped")+COUNTIFS('Capability Vector'!$B$5:$B$203,AY12,'Capability Vector'!$R$5:$R$203,"Yes")+COUNTIFS('Capability Vector'!$B$5:$B$203,AY12,'Capability Vector'!$R$5:$R$203,"Scoped")>0,OR(COUNTIF('Tool Authority Registry'!$B$5:$B$303,AY12)=0,COUNTIF('Interface Register'!$B$5:$B$303,AY12)=0)),"Tool discovery or credential access: add Tool Authority Registry and Interface Register rows",IF(AND(OR(AB12="Approved",AB12="Approved with conditions"),AC12="Active",COUNTIFS('Runtime Controls'!$B$5:$B$303,AY12,'Runtime Controls'!$E$5:$E$303,"Required",'Runtime Controls'!$F$5:$F$303,"<>Evidenced",'Runtime Controls'!$M$5:$M$303,"")+COUNTIFS('Runtime Controls'!$B$5:$B$303,AY12,'Runtime Controls'!$E$5:$E$303,"Required",'Runtime Controls'!$F$5:$F$303,"<>Evidenced",'Runtime Controls'!$M$5:$M$303,"<>",'Runtime Controls'!$L$5:$L$303,"")>0),"Production requirement (Gate 6): required control not Implemented and Evidenced, and no time-bounded compensating control (F.7.8)",IF(AND(OR(AB12="Approved",AB12="Approved with conditions"),AC12="Active",COUNTIFS('Runtime Controls'!$B$5:$B$303,AY12,'Runtime Controls'!$E$5:$E$303,"Required",'Runtime Controls'!$F$5:$F$303,"<>Evidenced",'Runtime Controls'!$M$5:$M$303,"<>",'Runtime Controls'!$L$5:$L$303,"<>")-COUNTIFS('Runtime Controls'!$B$5:$B$303,AY12,'Runtime Controls'!$E$5:$E$303,"Required",'Runtime Controls'!$F$5:$F$303,"<>Evidenced",'Runtime Controls'!$M$5:$M$303,"<>",'Runtime Controls'!$L$5:$L$303,">="&TODAY())>0),"Production requirement (Gate 6): compensating control expired, re-authorise (Expiry / Review must be a date on or after today; F.7.8)",IF(OR(AS12="",BB12=""),"Oversight mode or ASBOM version missing",IF(AND(AC12="Active",BA12=""),"Active without use-specific decision ref (F.7.8)",IF(AND(BJ12<>"",BK12=""),"Permitted autonomy decision ref missing",IF(AND(AC12="Active",BJ12=""),"Active without permitted autonomy level","OK")))))))))))))))))) | BL12: =IF(A12="","",IF(OR(M12="",LEFT(M12,2)="T3",LEFT(M12,2)="T4",LEFT(M12,2)="T5",AND(R12<>"",R12<>"No",R12<>"None",R12<>"0",R12<>"N/A")),"Full",IF(OR(O12="Yes",Q12="Yes",P12="Working memory",P12="Retrieved knowledge",P12="Persistent memory",COUNTIFS('Capability Vector'!$B$5:$B$203,AY12,'Capability Vector'!$P$5:$P$203,"Yes")+COUNTIFS('Capability Vector'!$B$5:$B$203,AY12,'Capability Vector'!$P$5:$P$203,"Scoped")+COUNTIFS('Capability Vector'!$B$5:$B$203,AY12,'Capability Vector'!$R$5:$R$203,"Yes")+COUNTIFS('Capability Vector'!$B$5:$B$203,AY12,'Capability Vector'!$R$5:$R$203,"Scoped")>0),"Core plus features","Core")))
BI13: =IF(A13="","",IF(AY13="","AG-ID missing",IF(COUNTIF($AY$5:$AY$203,AY13)>1,"Duplicate AG-ID",IF(AND(OR(AB13="Approved",AB13="Approved with conditions",AC13="Active"),OR(B13="",C13="",H13="",I13="",M13="",S13="",T13="",U13="",X13="",AA13="",AZ13="",BE13="")),"Core record incomplete: name, purpose, owner, platform, agency tier and profile ref, permission scope, credentials, how to stop it, how to undo it, UC-IDs and review date are needed before go-live",IF(AND(OR(AB13="Approved",AB13="Approved with conditions",AC13="Active"),COUNTIF('Agency Profile'!$B$5:$B$203,AY13)=0),"Agency Profile row missing: record the five agency scores behind the tier",IF(AND(OR(AB13="Approved",AB13="Approved with conditions",AC13="Active"),OR(B13="Not disclosed by supplier",C13="Not disclosed by supplier",H13="Not disclosed by supplier",I13="Not disclosed by supplier",M13="Not disclosed by supplier",S13="Not disclosed by supplier",T13="Not disclosed by supplier",U13="Not disclosed by supplier",X13="Not disclosed by supplier",AA13="Not disclosed by supplier",AZ13="Not disclosed by supplier",BE13="Not disclosed by supplier",AS13="Not disclosed by supplier",BJ13="Not disclosed by supplier")),"A core field says Not disclosed by supplier: the Council must answer the core fields itself",IF(AND(OR(AB13="Approved",AB13="Approved with conditions",AC13="Active"),BL13="Full",OR(COUNTIF('Capability Vector'!$B$5:$B$203,AY13)=0,COUNTIF(Components!$B$5:$B$303,AY13)=0,COUNTIFS('Runtime Controls'!$B$5:$B$303,AY13,'Runtime Controls'!$E$5:$E$303,"<>")<10)),"Full ASBOM (T3 and above, financial authority or tier not assessed): Capability Vector, Components and all ten Runtime Controls rows with Required State set are needed",IF(AND(OR(AB13="Approved",AB13="Approved with conditions",AC13="Active"),OR(Q13="Yes",BL13="Full"),COUNTIF('Authority & Delegations'!$C$5:$C$303,AY13)=0),"Delegation or Full level: add Authority & Delegations rows (they feed the Authority Graph)",IF(AND(OR(AB13="Approved",AB13="Approved with conditions",AC13="Active"),Q13="Yes",COUNTIF('Multi-Agent Controls'!$B$5:$B$303,AY13)=0),"Delegation: add a Multi-Agent Controls row",IF(AND(OR(AB13="Approved",AB13="Approved with conditions",AC13="Active"),O13="Yes",COUNTIF('Runtime Controls'!$B$5:$B$303,AY13)=0),"Persistence: add Runtime Controls rows for how it is stopped and contained",IF(AND(OR(AB13="Approved",AB13="Approved with conditions",AC13="Active"),OR(P13="Working memory",P13="Retrieved knowledge",P13="Persistent memory"),COUNTIF('Memory Controls'!$B$5:$B$303,AY13)=0),"Memory: add a Memory Controls row for each memory store",IF(AND(OR(AB13="Approved",AB13="Approved with conditions",AC13="Active"),COUNTIFS('Capability Vector'!$B$5:$B$203,AY13,'Capability Vector'!$P$5:$P$203,"Yes")+COUNTIFS('Capability Vector'!$B$5:$B$203,AY13,'Capability Vector'!$P$5:$P$203,"Scoped")+COUNTIFS('Capability Vector'!$B$5:$B$203,AY13,'Capability Vector'!$R$5:$R$203,"Yes")+COUNTIFS('Capability Vector'!$B$5:$B$203,AY13,'Capability Vector'!$R$5:$R$203,"Scoped")>0,OR(COUNTIF('Tool Authority Registry'!$B$5:$B$303,AY13)=0,COUNTIF('Interface Register'!$B$5:$B$303,AY13)=0)),"Tool discovery or credential access: add Tool Authority Registry and Interface Register rows",IF(AND(OR(AB13="Approved",AB13="Approved with conditions"),AC13="Active",COUNTIFS('Runtime Controls'!$B$5:$B$303,AY13,'Runtime Controls'!$E$5:$E$303,"Required",'Runtime Controls'!$F$5:$F$303,"<>Evidenced",'Runtime Controls'!$M$5:$M$303,"")+COUNTIFS('Runtime Controls'!$B$5:$B$303,AY13,'Runtime Controls'!$E$5:$E$303,"Required",'Runtime Controls'!$F$5:$F$303,"<>Evidenced",'Runtime Controls'!$M$5:$M$303,"<>",'Runtime Controls'!$L$5:$L$303,"")>0),"Production requirement (Gate 6): required control not Implemented and Evidenced, and no time-bounded compensating control (F.7.8)",IF(AND(OR(AB13="Approved",AB13="Approved with conditions"),AC13="Active",COUNTIFS('Runtime Controls'!$B$5:$B$303,AY13,'Runtime Controls'!$E$5:$E$303,"Required",'Runtime Controls'!$F$5:$F$303,"<>Evidenced",'Runtime Controls'!$M$5:$M$303,"<>",'Runtime Controls'!$L$5:$L$303,"<>")-COUNTIFS('Runtime Controls'!$B$5:$B$303,AY13,'Runtime Controls'!$E$5:$E$303,"Required",'Runtime Controls'!$F$5:$F$303,"<>Evidenced",'Runtime Controls'!$M$5:$M$303,"<>",'Runtime Controls'!$L$5:$L$303,">="&TODAY())>0),"Production requirement (Gate 6): compensating control expired, re-authorise (Expiry / Review must be a date on or after today; F.7.8)",IF(OR(AS13="",BB13=""),"Oversight mode or ASBOM version missing",IF(AND(AC13="Active",BA13=""),"Active without use-specific decision ref (F.7.8)",IF(AND(BJ13<>"",BK13=""),"Permitted autonomy decision ref missing",IF(AND(AC13="Active",BJ13=""),"Active without permitted autonomy level","OK")))))))))))))))))) | BL13: =IF(A13="","",IF(OR(M13="",LEFT(M13,2)="T3",LEFT(M13,2)="T4",LEFT(M13,2)="T5",AND(R13<>"",R13<>"No",R13<>"None",R13<>"0",R13<>"N/A")),"Full",IF(OR(O13="Yes",Q13="Yes",P13="Working memory",P13="Retrieved knowledge",P13="Persistent memory",COUNTIFS('Capability Vector'!$B$5:$B$203,AY13,'Capability Vector'!$P$5:$P$203,"Yes")+COUNTIFS('Capability Vector'!$B$5:$B$203,AY13,'Capability Vector'!$P$5:$P$203,"Scoped")+COUNTIFS('Capability Vector'!$B$5:$B$203,AY13,'Capability Vector'!$R$5:$R$203,"Yes")+COUNTIFS('Capability Vector'!$B$5:$B$203,AY13,'Capability Vector'!$R$5:$R$203,"Scoped")>0),"Core plus features","Core")))
BI14: =IF(A14="","",IF(AY14="","AG-ID missing",IF(COUNTIF($AY$5:$AY$203,AY14)>1,"Duplicate AG-ID",IF(AND(OR(AB14="Approved",AB14="Approved with conditions",AC14="Active"),OR(B14="",C14="",H14="",I14="",M14="",S14="",T14="",U14="",X14="",AA14="",AZ14="",BE14="")),"Core record incomplete: name, purpose, owner, platform, agency tier and profile ref, permission scope, credentials, how to stop it, how to undo it, UC-IDs and review date are needed before go-live",IF(AND(OR(AB14="Approved",AB14="Approved with conditions",AC14="Active"),COUNTIF('Agency Profile'!$B$5:$B$203,AY14)=0),"Agency Profile row missing: record the five agency scores behind the tier",IF(AND(OR(AB14="Approved",AB14="Approved with conditions",AC14="Active"),OR(B14="Not disclosed by supplier",C14="Not disclosed by supplier",H14="Not disclosed by supplier",I14="Not disclosed by supplier",M14="Not disclosed by supplier",S14="Not disclosed by supplier",T14="Not disclosed by supplier",U14="Not disclosed by supplier",X14="Not disclosed by supplier",AA14="Not disclosed by supplier",AZ14="Not disclosed by supplier",BE14="Not disclosed by supplier",AS14="Not disclosed by supplier",BJ14="Not disclosed by supplier")),"A core field says Not disclosed by supplier: the Council must answer the core fields itself",IF(AND(OR(AB14="Approved",AB14="Approved with conditions",AC14="Active"),BL14="Full",OR(COUNTIF('Capability Vector'!$B$5:$B$203,AY14)=0,COUNTIF(Components!$B$5:$B$303,AY14)=0,COUNTIFS('Runtime Controls'!$B$5:$B$303,AY14,'Runtime Controls'!$E$5:$E$303,"<>")<10)),"Full ASBOM (T3 and above, financial authority or tier not assessed): Capability Vector, Components and all ten Runtime Controls rows with Required State set are needed",IF(AND(OR(AB14="Approved",AB14="Approved with conditions",AC14="Active"),OR(Q14="Yes",BL14="Full"),COUNTIF('Authority & Delegations'!$C$5:$C$303,AY14)=0),"Delegation or Full level: add Authority & Delegations rows (they feed the Authority Graph)",IF(AND(OR(AB14="Approved",AB14="Approved with conditions",AC14="Active"),Q14="Yes",COUNTIF('Multi-Agent Controls'!$B$5:$B$303,AY14)=0),"Delegation: add a Multi-Agent Controls row",IF(AND(OR(AB14="Approved",AB14="Approved with conditions",AC14="Active"),O14="Yes",COUNTIF('Runtime Controls'!$B$5:$B$303,AY14)=0),"Persistence: add Runtime Controls rows for how it is stopped and contained",IF(AND(OR(AB14="Approved",AB14="Approved with conditions",AC14="Active"),OR(P14="Working memory",P14="Retrieved knowledge",P14="Persistent memory"),COUNTIF('Memory Controls'!$B$5:$B$303,AY14)=0),"Memory: add a Memory Controls row for each memory store",IF(AND(OR(AB14="Approved",AB14="Approved with conditions",AC14="Active"),COUNTIFS('Capability Vector'!$B$5:$B$203,AY14,'Capability Vector'!$P$5:$P$203,"Yes")+COUNTIFS('Capability Vector'!$B$5:$B$203,AY14,'Capability Vector'!$P$5:$P$203,"Scoped")+COUNTIFS('Capability Vector'!$B$5:$B$203,AY14,'Capability Vector'!$R$5:$R$203,"Yes")+COUNTIFS('Capability Vector'!$B$5:$B$203,AY14,'Capability Vector'!$R$5:$R$203,"Scoped")>0,OR(COUNTIF('Tool Authority Registry'!$B$5:$B$303,AY14)=0,COUNTIF('Interface Register'!$B$5:$B$303,AY14)=0)),"Tool discovery or credential access: add Tool Authority Registry and Interface Register rows",IF(AND(OR(AB14="Approved",AB14="Approved with conditions"),AC14="Active",COUNTIFS('Runtime Controls'!$B$5:$B$303,AY14,'Runtime Controls'!$E$5:$E$303,"Required",'Runtime Controls'!$F$5:$F$303,"<>Evidenced",'Runtime Controls'!$M$5:$M$303,"")+COUNTIFS('Runtime Controls'!$B$5:$B$303,AY14,'Runtime Controls'!$E$5:$E$303,"Required",'Runtime Controls'!$F$5:$F$303,"<>Evidenced",'Runtime Controls'!$M$5:$M$303,"<>",'Runtime Controls'!$L$5:$L$303,"")>0),"Production requirement (Gate 6): required control not Implemented and Evidenced, and no time-bounded compensating control (F.7.8)",IF(AND(OR(AB14="Approved",AB14="Approved with conditions"),AC14="Active",COUNTIFS('Runtime Controls'!$B$5:$B$303,AY14,'Runtime Controls'!$E$5:$E$303,"Required",'Runtime Controls'!$F$5:$F$303,"<>Evidenced",'Runtime Controls'!$M$5:$M$303,"<>",'Runtime Controls'!$L$5:$L$303,"<>")-COUNTIFS('Runtime Controls'!$B$5:$B$303,AY14,'Runtime Controls'!$E$5:$E$303,"Required",'Runtime Controls'!$F$5:$F$303,"<>Evidenced",'Runtime Controls'!$M$5:$M$303,"<>",'Runtime Controls'!$L$5:$L$303,">="&TODAY())>0),"Production requirement (Gate 6): compensating control expired, re-authorise (Expiry / Review must be a date on or after today; F.7.8)",IF(OR(AS14="",BB14=""),"Oversight mode or ASBOM version missing",IF(AND(AC14="Active",BA14=""),"Active without use-specific decision ref (F.7.8)",IF(AND(BJ14<>"",BK14=""),"Permitted autonomy decision ref missing",IF(AND(AC14="Active",BJ14=""),"Active without permitted autonomy level","OK")))))))))))))))))) | BL14: =IF(A14="","",IF(OR(M14="",LEFT(M14,2)="T3",LEFT(M14,2)="T4",LEFT(M14,2)="T5",AND(R14<>"",R14<>"No",R14<>"None",R14<>"0",R14<>"N/A")),"Full",IF(OR(O14="Yes",Q14="Yes",P14="Working memory",P14="Retrieved knowledge",P14="Persistent memory",COUNTIFS('Capability Vector'!$B$5:$B$203,AY14,'Capability Vector'!$P$5:$P$203,"Yes")+COUNTIFS('Capability Vector'!$B$5:$B$203,AY14,'Capability Vector'!$P$5:$P$203,"Scoped")+COUNTIFS('Capability Vector'!$B$5:$B$203,AY14,'Capability Vector'!$R$5:$R$203,"Yes")+COUNTIFS('Capability Vector'!$B$5:$B$203,AY14,'Capability Vector'!$R$5:$R$203,"Scoped")>0),"Core plus features","Core")))
BI15: =IF(A15="","",IF(AY15="","AG-ID missing",IF(COUNTIF($AY$5:$AY$203,AY15)>1,"Duplicate AG-ID",IF(AND(OR(AB15="Approved",AB15="Approved with conditions",AC15="Active"),OR(B15="",C15="",H15="",I15="",M15="",S15="",T15="",U15="",X15="",AA15="",AZ15="",BE15="")),"Core record incomplete: name, purpose, owner, platform, agency tier and profile ref, permission scope, credentials, how to stop it, how to undo it, UC-IDs and review date are needed before go-live",IF(AND(OR(AB15="Approved",AB15="Approved with conditions",AC15="Active"),COUNTIF('Agency Profile'!$B$5:$B$203,AY15)=0),"Agency Profile row missing: record the five agency scores behind the tier",IF(AND(OR(AB15="Approved",AB15="Approved with conditions",AC15="Active"),OR(B15="Not disclosed by supplier",C15="Not disclosed by supplier",H15="Not disclosed by supplier",I15="Not disclosed by supplier",M15="Not disclosed by supplier",S15="Not disclosed by supplier",T15="Not disclosed by supplier",U15="Not disclosed by supplier",X15="Not disclosed by supplier",AA15="Not disclosed by supplier",AZ15="Not disclosed by supplier",BE15="Not disclosed by supplier",AS15="Not disclosed by supplier",BJ15="Not disclosed by supplier")),"A core field says Not disclosed by supplier: the Council must answer the core fields itself",IF(AND(OR(AB15="Approved",AB15="Approved with conditions",AC15="Active"),BL15="Full",OR(COUNTIF('Capability Vector'!$B$5:$B$203,AY15)=0,COUNTIF(Components!$B$5:$B$303,AY15)=0,COUNTIFS('Runtime Controls'!$B$5:$B$303,AY15,'Runtime Controls'!$E$5:$E$303,"<>")<10)),"Full ASBOM (T3 and above, financial authority or tier not assessed): Capability Vector, Components and all ten Runtime Controls rows with Required State set are needed",IF(AND(OR(AB15="Approved",AB15="Approved with conditions",AC15="Active"),OR(Q15="Yes",BL15="Full"),COUNTIF('Authority & Delegations'!$C$5:$C$303,AY15)=0),"Delegation or Full level: add Authority & Delegations rows (they feed the Authority Graph)",IF(AND(OR(AB15="Approved",AB15="Approved with conditions",AC15="Active"),Q15="Yes",COUNTIF('Multi-Agent Controls'!$B$5:$B$303,AY15)=0),"Delegation: add a Multi-Agent Controls row",IF(AND(OR(AB15="Approved",AB15="Approved with conditions",AC15="Active"),O15="Yes",COUNTIF('Runtime Controls'!$B$5:$B$303,AY15)=0),"Persistence: add Runtime Controls rows for how it is stopped and contained",IF(AND(OR(AB15="Approved",AB15="Approved with conditions",AC15="Active"),OR(P15="Working memory",P15="Retrieved knowledge",P15="Persistent memory"),COUNTIF('Memory Controls'!$B$5:$B$303,AY15)=0),"Memory: add a Memory Controls row for each memory store",IF(AND(OR(AB15="Approved",AB15="Approved with conditions",AC15="Active"),COUNTIFS('Capability Vector'!$B$5:$B$203,AY15,'Capability Vector'!$P$5:$P$203,"Yes")+COUNTIFS('Capability Vector'!$B$5:$B$203,AY15,'Capability Vector'!$P$5:$P$203,"Scoped")+COUNTIFS('Capability Vector'!$B$5:$B$203,AY15,'Capability Vector'!$R$5:$R$203,"Yes")+COUNTIFS('Capability Vector'!$B$5:$B$203,AY15,'Capability Vector'!$R$5:$R$203,"Scoped")>0,OR(COUNTIF('Tool Authority Registry'!$B$5:$B$303,AY15)=0,COUNTIF('Interface Register'!$B$5:$B$303,AY15)=0)),"Tool discovery or credential access: add Tool Authority Registry and Interface Register rows",IF(AND(OR(AB15="Approved",AB15="Approved with conditions"),AC15="Active",COUNTIFS('Runtime Controls'!$B$5:$B$303,AY15,'Runtime Controls'!$E$5:$E$303,"Required",'Runtime Controls'!$F$5:$F$303,"<>Evidenced",'Runtime Controls'!$M$5:$M$303,"")+COUNTIFS('Runtime Controls'!$B$5:$B$303,AY15,'Runtime Controls'!$E$5:$E$303,"Required",'Runtime Controls'!$F$5:$F$303,"<>Evidenced",'Runtime Controls'!$M$5:$M$303,"<>",'Runtime Controls'!$L$5:$L$303,"")>0),"Production requirement (Gate 6): required control not Implemented and Evidenced, and no time-bounded compensating control (F.7.8)",IF(AND(OR(AB15="Approved",AB15="Approved with conditions"),AC15="Active",COUNTIFS('Runtime Controls'!$B$5:$B$303,AY15,'Runtime Controls'!$E$5:$E$303,"Required",'Runtime Controls'!$F$5:$F$303,"<>Evidenced",'Runtime Controls'!$M$5:$M$303,"<>",'Runtime Controls'!$L$5:$L$303,"<>")-COUNTIFS('Runtime Controls'!$B$5:$B$303,AY15,'Runtime Controls'!$E$5:$E$303,"Required",'Runtime Controls'!$F$5:$F$303,"<>Evidenced",'Runtime Controls'!$M$5:$M$303,"<>",'Runtime Controls'!$L$5:$L$303,">="&TODAY())>0),"Production requirement (Gate 6): compensating control expired, re-authorise (Expiry / Review must be a date on or after today; F.7.8)",IF(OR(AS15="",BB15=""),"Oversight mode or ASBOM version missing",IF(AND(AC15="Active",BA15=""),"Active without use-specific decision ref (F.7.8)",IF(AND(BJ15<>"",BK15=""),"Permitted autonomy decision ref missing",IF(AND(AC15="Active",BJ15=""),"Active without permitted autonomy level","OK")))))))))))))))))) | BL15: =IF(A15="","",IF(OR(M15="",LEFT(M15,2)="T3",LEFT(M15,2)="T4",LEFT(M15,2)="T5",AND(R15<>"",R15<>"No",R15<>"None",R15<>"0",R15<>"N/A")),"Full",IF(OR(O15="Yes",Q15="Yes",P15="Working memory",P15="Retrieved knowledge",P15="Persistent memory",COUNTIFS('Capability Vector'!$B$5:$B$203,AY15,'Capability Vector'!$P$5:$P$203,"Yes")+COUNTIFS('Capability Vector'!$B$5:$B$203,AY15,'Capability Vector'!$P$5:$P$203,"Scoped")+COUNTIFS('Capability Vector'!$B$5:$B$203,AY15,'Capability Vector'!$R$5:$R$203,"Yes")+COUNTIFS('Capability Vector'!$B$5:$B$203,AY15,'Capability Vector'!$R$5:$R$203,"Scoped")>0),"Core plus features","Core")))
BI16: =IF(A16="","",IF(AY16="","AG-ID missing",IF(COUNTIF($AY$5:$AY$203,AY16)>1,"Duplicate AG-ID",IF(AND(OR(AB16="Approved",AB16="Approved with conditions",AC16="Active"),OR(B16="",C16="",H16="",I16="",M16="",S16="",T16="",U16="",X16="",AA16="",AZ16="",BE16="")),"Core record incomplete: name, purpose, owner, platform, agency tier and profile ref, permission scope, credentials, how to stop it, how to undo it, UC-IDs and review date are needed before go-live",IF(AND(OR(AB16="Approved",AB16="Approved with conditions",AC16="Active"),COUNTIF('Agency Profile'!$B$5:$B$203,AY16)=0),"Agency Profile row missing: record the five agency scores behind the tier",IF(AND(OR(AB16="Approved",AB16="Approved with conditions",AC16="Active"),OR(B16="Not disclosed by supplier",C16="Not disclosed by supplier",H16="Not disclosed by supplier",I16="Not disclosed by supplier",M16="Not disclosed by supplier",S16="Not disclosed by supplier",T16="Not disclosed by supplier",U16="Not disclosed by supplier",X16="Not disclosed by supplier",AA16="Not disclosed by supplier",AZ16="Not disclosed by supplier",BE16="Not disclosed by supplier",AS16="Not disclosed by supplier",BJ16="Not disclosed by supplier")),"A core field says Not disclosed by supplier: the Council must answer the core fields itself",IF(AND(OR(AB16="Approved",AB16="Approved with conditions",AC16="Active"),BL16="Full",OR(COUNTIF('Capability Vector'!$B$5:$B$203,AY16)=0,COUNTIF(Components!$B$5:$B$303,AY16)=0,COUNTIFS('Runtime Controls'!$B$5:$B$303,AY16,'Runtime Controls'!$E$5:$E$303,"<>")<10)),"Full ASBOM (T3 and above, financial authority or tier not assessed): Capability Vector, Components and all ten Runtime Controls rows with Required State set are needed",IF(AND(OR(AB16="Approved",AB16="Approved with conditions",AC16="Active"),OR(Q16="Yes",BL16="Full"),COUNTIF('Authority & Delegations'!$C$5:$C$303,AY16)=0),"Delegation or Full level: add Authority & Delegations rows (they feed the Authority Graph)",IF(AND(OR(AB16="Approved",AB16="Approved with conditions",AC16="Active"),Q16="Yes",COUNTIF('Multi-Agent Controls'!$B$5:$B$303,AY16)=0),"Delegation: add a Multi-Agent Controls row",IF(AND(OR(AB16="Approved",AB16="Approved with conditions",AC16="Active"),O16="Yes",COUNTIF('Runtime Controls'!$B$5:$B$303,AY16)=0),"Persistence: add Runtime Controls rows for how it is stopped and contained",IF(AND(OR(AB16="Approved",AB16="Approved with conditions",AC16="Active"),OR(P16="Working memory",P16="Retrieved knowledge",P16="Persistent memory"),COUNTIF('Memory Controls'!$B$5:$B$303,AY16)=0),"Memory: add a Memory Controls row for each memory store",IF(AND(OR(AB16="Approved",AB16="Approved with conditions",AC16="Active"),COUNTIFS('Capability Vector'!$B$5:$B$203,AY16,'Capability Vector'!$P$5:$P$203,"Yes")+COUNTIFS('Capability Vector'!$B$5:$B$203,AY16,'Capability Vector'!$P$5:$P$203,"Scoped")+COUNTIFS('Capability Vector'!$B$5:$B$203,AY16,'Capability Vector'!$R$5:$R$203,"Yes")+COUNTIFS('Capability Vector'!$B$5:$B$203,AY16,'Capability Vector'!$R$5:$R$203,"Scoped")>0,OR(COUNTIF('Tool Authority Registry'!$B$5:$B$303,AY16)=0,COUNTIF('Interface Register'!$B$5:$B$303,AY16)=0)),"Tool discovery or credential access: add Tool Authority Registry and Interface Register rows",IF(AND(OR(AB16="Approved",AB16="Approved with conditions"),AC16="Active",COUNTIFS('Runtime Controls'!$B$5:$B$303,AY16,'Runtime Controls'!$E$5:$E$303,"Required",'Runtime Controls'!$F$5:$F$303,"<>Evidenced",'Runtime Controls'!$M$5:$M$303,"")+COUNTIFS('Runtime Controls'!$B$5:$B$303,AY16,'Runtime Controls'!$E$5:$E$303,"Required",'Runtime Controls'!$F$5:$F$303,"<>Evidenced",'Runtime Controls'!$M$5:$M$303,"<>",'Runtime Controls'!$L$5:$L$303,"")>0),"Production requirement (Gate 6): required control not Implemented and Evidenced, and no time-bounded compensating control (F.7.8)",IF(AND(OR(AB16="Approved",AB16="Approved with conditions"),AC16="Active",COUNTIFS('Runtime Controls'!$B$5:$B$303,AY16,'Runtime Controls'!$E$5:$E$303,"Required",'Runtime Controls'!$F$5:$F$303,"<>Evidenced",'Runtime Controls'!$M$5:$M$303,"<>",'Runtime Controls'!$L$5:$L$303,"<>")-COUNTIFS('Runtime Controls'!$B$5:$B$303,AY16,'Runtime Controls'!$E$5:$E$303,"Required",'Runtime Controls'!$F$5:$F$303,"<>Evidenced",'Runtime Controls'!$M$5:$M$303,"<>",'Runtime Controls'!$L$5:$L$303,">="&TODAY())>0),"Production requirement (Gate 6): compensating control expired, re-authorise (Expiry / Review must be a date on or after today; F.7.8)",IF(OR(AS16="",BB16=""),"Oversight mode or ASBOM version missing",IF(AND(AC16="Active",BA16=""),"Active without use-specific decision ref (F.7.8)",IF(AND(BJ16<>"",BK16=""),"Permitted autonomy decision ref missing",IF(AND(AC16="Active",BJ16=""),"Active without permitted autonomy level","OK")))))))))))))))))) | BL16: =IF(A16="","",IF(OR(M16="",LEFT(M16,2)="T3",LEFT(M16,2)="T4",LEFT(M16,2)="T5",AND(R16<>"",R16<>"No",R16<>"None",R16<>"0",R16<>"N/A")),"Full",IF(OR(O16="Yes",Q16="Yes",P16="Working memory",P16="Retrieved knowledge",P16="Persistent memory",COUNTIFS('Capability Vector'!$B$5:$B$203,AY16,'Capability Vector'!$P$5:$P$203,"Yes")+COUNTIFS('Capability Vector'!$B$5:$B$203,AY16,'Capability Vector'!$P$5:$P$203,"Scoped")+COUNTIFS('Capability Vector'!$B$5:$B$203,AY16,'Capability Vector'!$R$5:$R$203,"Yes")+COUNTIFS('Capability Vector'!$B$5:$B$203,AY16,'Capability Vector'!$R$5:$R$203,"Scoped")>0),"Core plus features","Core")))
BI17: =IF(A17="","",IF(AY17="","AG-ID missing",IF(COUNTIF($AY$5:$AY$203,AY17)>1,"Duplicate AG-ID",IF(AND(OR(AB17="Approved",AB17="Approved with conditions",AC17="Active"),OR(B17="",C17="",H17="",I17="",M17="",S17="",T17="",U17="",X17="",AA17="",AZ17="",BE17="")),"Core record incomplete: name, purpose, owner, platform, agency tier and profile ref, permission scope, credentials, how to stop it, how to undo it, UC-IDs and review date are needed before go-live",IF(AND(OR(AB17="Approved",AB17="Approved with conditions",AC17="Active"),COUNTIF('Agency Profile'!$B$5:$B$203,AY17)=0),"Agency Profile row missing: record the five agency scores behind the tier",IF(AND(OR(AB17="Approved",AB17="Approved with conditions",AC17="Active"),OR(B17="Not disclosed by supplier",C17="Not disclosed by supplier",H17="Not disclosed by supplier",I17="Not disclosed by supplier",M17="Not disclosed by supplier",S17="Not disclosed by supplier",T17="Not disclosed by supplier",U17="Not disclosed by supplier",X17="Not disclosed by supplier",AA17="Not disclosed by supplier",AZ17="Not disclosed by supplier",BE17="Not disclosed by supplier",AS17="Not disclosed by supplier",BJ17="Not disclosed by supplier")),"A core field says Not disclosed by supplier: the Council must answer the core fields itself",IF(AND(OR(AB17="Approved",AB17="Approved with conditions",AC17="Active"),BL17="Full",OR(COUNTIF('Capability Vector'!$B$5:$B$203,AY17)=0,COUNTIF(Components!$B$5:$B$303,AY17)=0,COUNTIFS('Runtime Controls'!$B$5:$B$303,AY17,'Runtime Controls'!$E$5:$E$303,"<>")<10)),"Full ASBOM (T3 and above, financial authority or tier not assessed): Capability Vector, Components and all ten Runtime Controls rows with Required State set are needed",IF(AND(OR(AB17="Approved",AB17="Approved with conditions",AC17="Active"),OR(Q17="Yes",BL17="Full"),COUNTIF('Authority & Delegations'!$C$5:$C$303,AY17)=0),"Delegation or Full level: add Authority & Delegations rows (they feed the Authority Graph)",IF(AND(OR(AB17="Approved",AB17="Approved with conditions",AC17="Active"),Q17="Yes",COUNTIF('Multi-Agent Controls'!$B$5:$B$303,AY17)=0),"Delegation: add a Multi-Agent Controls row",IF(AND(OR(AB17="Approved",AB17="Approved with conditions",AC17="Active"),O17="Yes",COUNTIF('Runtime Controls'!$B$5:$B$303,AY17)=0),"Persistence: add Runtime Controls rows for how it is stopped and contained",IF(AND(OR(AB17="Approved",AB17="Approved with conditions",AC17="Active"),OR(P17="Working memory",P17="Retrieved knowledge",P17="Persistent memory"),COUNTIF('Memory Controls'!$B$5:$B$303,AY17)=0),"Memory: add a Memory Controls row for each memory store",IF(AND(OR(AB17="Approved",AB17="Approved with conditions",AC17="Active"),COUNTIFS('Capability Vector'!$B$5:$B$203,AY17,'Capability Vector'!$P$5:$P$203,"Yes")+COUNTIFS('Capability Vector'!$B$5:$B$203,AY17,'Capability Vector'!$P$5:$P$203,"Scoped")+COUNTIFS('Capability Vector'!$B$5:$B$203,AY17,'Capability Vector'!$R$5:$R$203,"Yes")+COUNTIFS('Capability Vector'!$B$5:$B$203,AY17,'Capability Vector'!$R$5:$R$203,"Scoped")>0,OR(COUNTIF('Tool Authority Registry'!$B$5:$B$303,AY17)=0,COUNTIF('Interface Register'!$B$5:$B$303,AY17)=0)),"Tool discovery or credential access: add Tool Authority Registry and Interface Register rows",IF(AND(OR(AB17="Approved",AB17="Approved with conditions"),AC17="Active",COUNTIFS('Runtime Controls'!$B$5:$B$303,AY17,'Runtime Controls'!$E$5:$E$303,"Required",'Runtime Controls'!$F$5:$F$303,"<>Evidenced",'Runtime Controls'!$M$5:$M$303,"")+COUNTIFS('Runtime Controls'!$B$5:$B$303,AY17,'Runtime Controls'!$E$5:$E$303,"Required",'Runtime Controls'!$F$5:$F$303,"<>Evidenced",'Runtime Controls'!$M$5:$M$303,"<>",'Runtime Controls'!$L$5:$L$303,"")>0),"Production requirement (Gate 6): required control not Implemented and Evidenced, and no time-bounded compensating control (F.7.8)",IF(AND(OR(AB17="Approved",AB17="Approved with conditions"),AC17="Active",COUNTIFS('Runtime Controls'!$B$5:$B$303,AY17,'Runtime Controls'!$E$5:$E$303,"Required",'Runtime Controls'!$F$5:$F$303,"<>Evidenced",'Runtime Controls'!$M$5:$M$303,"<>",'Runtime Controls'!$L$5:$L$303,"<>")-COUNTIFS('Runtime Controls'!$B$5:$B$303,AY17,'Runtime Controls'!$E$5:$E$303,"Required",'Runtime Controls'!$F$5:$F$303,"<>Evidenced",'Runtime Controls'!$M$5:$M$303,"<>",'Runtime Controls'!$L$5:$L$303,">="&TODAY())>0),"Production requirement (Gate 6): compensating control expired, re-authorise (Expiry / Review must be a date on or after today; F.7.8)",IF(OR(AS17="",BB17=""),"Oversight mode or ASBOM version missing",IF(AND(AC17="Active",BA17=""),"Active without use-specific decision ref (F.7.8)",IF(AND(BJ17<>"",BK17=""),"Permitted autonomy decision ref missing",IF(AND(AC17="Active",BJ17=""),"Active without permitted autonomy level","OK")))))))))))))))))) | BL17: =IF(A17="","",IF(OR(M17="",LEFT(M17,2)="T3",LEFT(M17,2)="T4",LEFT(M17,2)="T5",AND(R17<>"",R17<>"No",R17<>"None",R17<>"0",R17<>"N/A")),"Full",IF(OR(O17="Yes",Q17="Yes",P17="Working memory",P17="Retrieved knowledge",P17="Persistent memory",COUNTIFS('Capability Vector'!$B$5:$B$203,AY17,'Capability Vector'!$P$5:$P$203,"Yes")+COUNTIFS('Capability Vector'!$B$5:$B$203,AY17,'Capability Vector'!$P$5:$P$203,"Scoped")+COUNTIFS('Capability Vector'!$B$5:$B$203,AY17,'Capability Vector'!$R$5:$R$203,"Yes")+COUNTIFS('Capability Vector'!$B$5:$B$203,AY17,'Capability Vector'!$R$5:$R$203,"Scoped")>0),"Core plus features","Core")))
... BI203: =IF(A203="","",IF(AY203="","AG-ID missing",IF(COUNTIF($AY$5:$AY$203,AY203)>1,"Duplicate AG-ID",IF(AND(OR(AB203="Approved",AB203="Approved with conditions",AC203="Active"),OR(B203="",C203="",H203="",I203="",M203="",S203="",T203="",U203="",X203="",AA203="",AZ203="",BE203="")),"Core record incomplete: name, purpose, owner, platform, agency tier and profile ref, permission scope, credentials, how to stop it, how to undo it, UC-IDs and review date are needed before go-live",IF(AND(OR(AB203="Approved",AB203="Approved with conditions",AC203="Active"),COUNTIF('Agency Profile'!$B$5:$B$203,AY203)=0),"Agency Profile row missing: record the five agency scores behind the tier",IF(AND(OR(AB203="Approved",AB203="Approved with conditions",AC203="Active"),OR(B203="Not disclosed by supplier",C203="Not disclosed by supplier",H203="Not disclosed by supplier",I203="Not disclosed by supplier",M203="Not disclosed by supplier",S203="Not disclosed by supplier",T203="Not disclosed by supplier",U203="Not disclosed by supplier",X203="Not disclosed by supplier",AA203="Not disclosed by supplier",AZ203="Not disclosed by supplier",BE203="Not disclosed by supplier",AS203="Not disclosed by supplier",BJ203="Not disclosed by supplier")),"A core field says Not disclosed by supplier: the Council must answer the core fields itself",IF(AND(OR(AB203="Approved",AB203="Approved with conditions",AC203="Active"),BL203="Full",OR(COUNTIF('Capability Vector'!$B$5:$B$203,AY203)=0,COUNTIF(Components!$B$5:$B$303,AY203)=0,COUNTIFS('Runtime Controls'!$B$5:$B$303,AY203,'Runtime Controls'!$E$5:$E$303,"<>")<10)),"Full ASBOM (T3 and above, financial authority or tier not assessed): Capability Vector, Components and all ten Runtime Controls rows with Required State set are needed",IF(AND(OR(AB203="Approved",AB203="Approved with conditions",AC203="Active"),OR(Q203="Yes",BL203="Full"),COUNTIF('Authority & Delegations'!$C$5:$C$303,AY203)=0),"Delegation or Full level: add Authority & Delegations rows (they feed the Authority Graph)",IF(AND(OR(AB203="Approved",AB203="Approved with conditions",AC203="Active"),Q203="Yes",COUNTIF('Multi-Agent Controls'!$B$5:$B$303,AY203)=0),"Delegation: add a Multi-Agent Controls row",IF(AND(OR(AB203="Approved",AB203="Approved with conditions",AC203="Active"),O203="Yes",COUNTIF('Runtime Controls'!$B$5:$B$303,AY203)=0),"Persistence: add Runtime Controls rows for how it is stopped and contained",IF(AND(OR(AB203="Approved",AB203="Approved with conditions",AC203="Active"),OR(P203="Working memory",P203="Retrieved knowledge",P203="Persistent memory"),COUNTIF('Memory Controls'!$B$5:$B$303,AY203)=0),"Memory: add a Memory Controls row for each memory store",IF(AND(OR(AB203="Approved",AB203="Approved with conditions",AC203="Active"),COUNTIFS('Capability Vector'!$B$5:$B$203,AY203,'Capability Vector'!$P$5:$P$203,"Yes")+COUNTIFS('Capability Vector'!$B$5:$B$203,AY203,'Capability Vector'!$P$5:$P$203,"Scoped")+COUNTIFS('Capability Vector'!$B$5:$B$203,AY203,'Capability Vector'!$R$5:$R$203,"Yes")+COUNTIFS('Capability Vector'!$B$5:$B$203,AY203,'Capability Vector'!$R$5:$R$203,"Scoped")>0,OR(COUNTIF('Tool Authority Registry'!$B$5:$B$303,AY203)=0,COUNTIF('Interface Register'!$B$5:$B$303,AY203)=0)),"Tool discovery or credential access: add Tool Authority Registry and Interface Register rows",IF(AND(OR(AB203="Approved",AB203="Approved with conditions"),AC203="Active",COUNTIFS('Runtime Controls'!$B$5:$B$303,AY203,'Runtime Controls'!$E$5:$E$303,"Required",'Runtime Controls'!$F$5:$F$303,"<>Evidenced",'Runtime Controls'!$M$5:$M$303,"")+COUNTIFS('Runtime Controls'!$B$5:$B$303,AY203,'Runtime Controls'!$E$5:$E$303,"Required",'Runtime Controls'!$F$5:$F$303,"<>Evidenced",'Runtime Controls'!$M$5:$M$303,"<>",'Runtime Controls'!$L$5:$L$303,"")>0),"Production requirement (Gate 6): required control not Implemented and Evidenced, and no time-bounded compensating control (F.7.8)",IF(AND(OR(AB203="Approved",AB203="Approved with conditions"),AC203="Active",COUNTIFS('Runtime Controls'!$B$5:$B$303,AY203,'Runtime Controls'!$E$5:$E$303,"Required",'Runtime Controls'!$F$5:$F$303,"<>Evidenced",'Runtime Controls'!$M$5:$M$303,"<>",'Runtime Controls'!$L$5:$L$303,"<>")-COUNTIFS('Runtime Controls'!$B$5:$B$303,AY203,'Runtime Controls'!$E$5:$E$303,"Required",'Runtime Controls'!$F$5:$F$303,"<>Evidenced",'Runtime Controls'!$M$5:$M$303,"<>",'Runtime Controls'!$L$5:$L$303,">="&TODAY())>0),"Production requirement (Gate 6): compensating control expired, re-authorise (Expiry / Review must be a date on or after today; F.7.8)",IF(OR(AS203="",BB203=""),"Oversight mode or ASBOM version missing",IF(AND(AC203="Active",BA203=""),"Active without use-specific decision ref (F.7.8)",IF(AND(BJ203<>"",BK203=""),"Permitted autonomy decision ref missing",IF(AND(AC203="Active",BJ203=""),"Active without permitted autonomy level","OK")))))))))))))))))) | BL203: =IF(A203="","",IF(OR(M203="",LEFT(M203,2)="T3",LEFT(M203,2)="T4",LEFT(M203,2)="T5",AND(R203<>"",R203<>"No",R203<>"None",R203<>"0",R203<>"N/A")),"Full",IF(OR(O203="Yes",Q203="Yes",P203="Working memory",P203="Retrieved knowledge",P203="Persistent memory",COUNTIFS('Capability Vector'!$B$5:$B$203,AY203,'Capability Vector'!$P$5:$P$203,"Yes")+COUNTIFS('Capability Vector'!$B$5:$B$203,AY203,'Capability Vector'!$P$5:$P$203,"Scoped")+COUNTIFS('Capability Vector'!$B$5:$B$203,AY203,'Capability Vector'!$R$5:$R$203,"Yes")+COUNTIFS('Capability Vector'!$B$5:$B$203,AY203,'Capability Vector'!$R$5:$R$203,"Scoped")>0),"Core plus features","Core")))

Sheet Platform Agent Inventory
A1: Platform Agent Inventory — agents built on an approved platform (Playbook Appendix F.8)
A2: One row per agent built by staff on a platform already on the AI Register (for example Microsoft 365 Copilot), keyed to the platform’s AIR-ID. The platform is governed once; each agent is personal, an approved pattern, or individually governed. Proposed — for Council confirmation.
A3: Columns match the Multi-Board Triage tool’s platform agent screening record exactly, so a downloaded row pastes here. Any trigger answered Yes or Unsure makes the agent individually governed: it then gets its own UC-ID and AG-ID and its own row on Agent Record. Personal and approved-pattern agents get no Agent Record row of their own; they are covered by the platform’s row. The AI Governance Lead reviews this sheet at least quarterly with the platform owner’s admin inventory, for new shared agents, agents without an owner, and agents with new connectors or actions.
A4: Platform AIR-ID | B4: Platform | C4: Agent name | D4: What it does | E4: Built by | F4: Named owner | G4: Shared with | H4: Pattern UC-ID | I4: Agent UC-ID | J4: Class | K4: LGA tier | L4: Triggers met (Yes or Unsure) | M4: Can it act? (F.8) | N4: Individual triage needed | O4: Next step | P4: Next inventory review | Q4: Screened on
A5: AIR-EXAMPLE | B5: Microsoft 365 Copilot | C5: Example — delete before use | D5: Answers staff questions from the team’s own SharePoint policy library; takes no actions. | E5: Team lead | F5: Head of service | G5: A team or service | H5: UC-EXAMPLE | J5: Approved-pattern agent (LGA Tier 2) | K5: Tier 2 | M5: Assisted (T1) at platform level, covered by the platform’s Gate 2 and Gate 6 evidence | N5: No | O5: List this instance in the platform’s agent inventory under the pattern with a named Service Owner. | P5: By 01/01/2027 (quarterly inventory review) | Q5: 16/10/2026

Sheet Capability Vector
A1: Capability Vector — what the agent can technically do
A2: Capability is not intention. Record what it CAN do, not what it is told to do.
A3: One row per AG-ID (under its AIR-ID). Each capability: No / Yes / Scoped. The agency multipliers on the right change the risk picture sharply and should be explicit flags; Field Guidance maps all ten AIG-AGT-02 multiplier flags to their columns.
A4: AIR-ID | B4: AG-ID | C4: Read | D4: Write | E4: Execute | F4: Communicate | G4: Purchase | H4: Delegate | I4: Persuade | J4: Code | K4: Discover | L4: Persist | M4: Replicate | N4: Learn | O4: Escalate | P4: Multiplier: Credential access | Q4: Multiplier: Self-modification | R4: Multiplier: Tool discovery | S4: Multiplier: Goal adaptation | T4: Multiplier: External comms | U4: Notes

Sheet Agency Profile
A1: Agency Profile — five-dimension agentic profile per agent
A2: One row per AG-ID. Proposed — for Council confirmation. Record each dimension score (0–5), its rationale and evidence; never replace a dimension with a multiplier. Controllability: 5 = hardest to stop or reverse. The highest applicable mandatory floor governs; the governing pathway is the higher of the risk-tier pathway and the minimum risk-tier pathway set by the agency tier (T2 Medium, T3 High, T4 High or Critical under §4.4.6, T5 Critical; AIG-DEC-01 Agentic pathway) (D7).
A3: This sheet is the record of the agency profile: rationale and evidence are held here. AIG-ASS-02 Step 5 holds only the scores used for tiering and points to this sheet; cite the AIG-ASS-02 / AIG-AGT-03 record the scores came from. The agency tier is a profile, not an average.
A4: AIR-ID | B4: AG-ID | C4: ASBOM record version | D4: Consequence (0–5) | E4: Consequence rationale | F4: Autonomy (0–5) | G4: Autonomy rationale | H4: Authority (0–5) | I4: Authority rationale | J4: Reach (0–5) | K4: Reach rationale | L4: Controllability (0–5; 5 = hardest to stop/reverse) | M4: Controllability rationale | N4: Evidence ref | O4: AIG-ASS-02 Step 5 / AIG-AGT-03 ref | P4: Mandatory tier floor (trigger) | Q4: Resulting agency tier | R4: Assessed by / date

Sheet Components
A1: Components — the bill of materials
A2: Every model, dataset, interface, tool, API, MCP server, sub-agent and credential the agent uses.
A3: One row per component per agent (AIR-ID + AG-ID). Each carries its own authority, maximum impact, reversibility and kill mechanism, so the agent's full composition can be read from one place (ASI04 supply chain).
A4: AIR-ID | B4: AG-ID | C4: Component Type | D4: Component ID | E4: Name / Version | F4: Owner | G4: Data accessed | H4: Permissions / authority | I4: Environment | J4: Maximum impact | K4: Reversibility | L4: Kill / disable mechanism | M4: Monitoring | N4: Approval requirement | O4: Notes

Sheet Authority & Delegations
A1: Authority & Delegations — edges for the Agent Authority Graph
A2: Every edge is a delegation of capability or authority.
A3: One row per delegation edge. Who delegated what authority to whom, through which mechanism, for what purpose, under what constraints, UC-ID scope and environment, and how it can be revoked. Edge type and node types distinguish authority edges from access/component relationships and separate agent creation/replication. This is the data the Agent Authority Graph (AIG-AGT-05) renders.
A4: Authority Edge ID | B4: AIR-ID (agent) | C4: AG-ID (agent) | D4: From (delegator) | E4: To (delegatee) | F4: Authority delegated | G4: Mechanism | H4: Purpose | I4: Constraints / ceiling | J4: Revocable how | K4: Expiry | L4: Inherited? | M4: Notes | N4: Delegator node type | O4: Delegatee node type | P4: Edge type | Q4: UC-ID scope | R4: Scope (actions / data / limits) | S4: Environment (stage) | T4: Exposure | U4: ASBOM record version

Sheet Field Guidance
A1: Field Guidance
A2: How to complete the Agent Record and its child sheets.
A3: Field | B3: Meaning | C3: Allowed values / format
A4: AIR-ID | B4: Permanent identifier, shared with the AI Register and every governance artefact. | C4: Free text, e.g. AIR-0001
A5: Approved Purpose (mandate) | B5: The single legitimate purpose the agent is authorised for. | C5: Free text
A6: Prohibited Purposes | B6: Uses explicitly disallowed for this agent. | C6: Free text
A7: Decisions never delegated | B7: Decisions that must always remain with a human. | C7: Free text
A8: Max acceptable consequence | B8: The worst outcome tolerated if it fails; anchors governance intensity. | C8: Free text
A9: Assessed autonomy level | B9: Assessed or requested autonomy from the Agentic Triage (AIG-AGT-03). It is not permission: the permitted level is granted at Gate 6 (go-live) (see Permitted autonomy level). | C9: A0-A5 (see Lists)
A10: Agency Tier | B10: Set by the Agentic Triage from the agency profile. | C10: T0-T5 (see Lists)
A11: Persistence? | B11: Can it keep acting after the initiating interaction ends? | C11: Yes / No
A12: Memory Type | B12: The most persistent memory it holds. | C12: None / Context / Working memory / Retrieved knowledge / Persistent memory (F.7.5 classes); record sharing across agents in Memory Controls (Cross-Agent Sharing)
A13: Can delegate? | B13: Can it delegate tasks or authority to other agents? Creating or replicating agents is governed separately (Agent Creation Authority, F.7.7). | C13: Yes / No
A14: Financial Authority (limit) | B14: Whether it can move or spend money, and the ceiling. | C14: Free text; No (or None, 0, N/A) if none. Anything else counts as financial authority and sets the Full record level.
... A50: Platform Agent Inventory (sheet) | B50: Agents built by staff on a platform already on the AI Register (Playbook Appendix F.8). One row per agent, keyed to the platform’s AIR-ID. Class follows the seven F.8 triggers: any Yes or Unsure means individually governed (its own UC-ID, AG-ID and Agent Record row). Personal and approved-pattern agents are covered by the platform’s Agent Record row; pattern agents carry the pattern’s UC-ID. Columns match the Multi-Board Triage tool’s platform agent screening download. Reviewed at least quarterly by the AI Governance Lead. | C50: Class, Shared with and LGA tier from Lists; Individual triage needed Yes/No

Sheet Lists
A1: Lists — controlled vocabulary
A2: Dropdown sources. Do not free-type where a list exists. Row 3 = list name; values start at row 4. Approval uses the controlled decision outcomes of AIG-DEC-03 plus Pending/Unknown; OpStatus includes Not live.
A3: Autonomy | B3: AgencyTier | C3: EnvironmentStage | D3: MemoryType | E3: ComponentType (node type) | F3: YN | G3: CapVal | H3: Approval | I3: OpStatus | J3: Reversibility | K3: RuntimeControlState | L3: OversightMode | M3: YesNoScoped | N3: Exposure | O3: EdgeType | P3: RequiredState | Q3: PlatformAgentClass | R3: PlatformAgentAudience | S3: LGATier
A4: A0 advisory | B4: T0 informational | C4: Production | D4: None | E4: Model | F4: Yes | G4: No | H4: Pending | I4: Not live | J4: Fully reversible | K4: Designed | L4: Pre-action approval | M4: Yes | N4: Customer-facing | O4: Authority delegation | P4: Required | Q4: Personal agent (LGA Tier 1) | R4: Just the person who built it | S4: Tier 1
A5: A1 assisted | B5: T1 assisted | C5: Pre-production / test | D5: Context | E5: Dataset | F5: No | G5: Yes | H5: Approved | I5: Active | J5: Partly reversible | K5: Specified | L5: Bounded execution with intervention | M5: No | N5: Internal | O5: Access relationship | P5: Not applicable (rationale in AIG-ASS-11) | Q5: Approved-pattern agent (LGA Tier 2) | R5: A team or service | S5: Tier 2
A6: A2 bounded execution | B6: T2 bounded agent | C6: Sandbox | D6: Working memory | E6: Interface | G6: Scoped | H6: Approved with conditions | I6: Suspended | J6: Difficult to reverse | K6: Implemented | L6: Post-action review | M6: Scoped | N6: Physical / OT | O6: Agent creation | Q6: Pattern not yet approved | R6: The whole organisation | S6: Tier 2 (once the pattern is approved)
A7: A3 conditional autonomy | B7: T3 consequential agent | D7: Retrieved knowledge | E7: Tool | H7: Deferred | I7: Decommissioned | J7: Irreversible | K7: Evidenced | L7: Monitoring-only | O7: Replication | Q7: Individually governed agent (LGA Tier 3) | S7: Tier 3
A8: A4 delegated autonomy | B8: T4 high-agency | D8: Persistent memory | E8: API | H8: Rejected | O8: Component relationship | Q8: Not an agent on an approved platform
A9: A5 open-ended autonomy | B9: T5 exceptional / high-consequence | E9: MCP Server | H9: Suspended
E10: Sub-agent | H10: Retired
E11: Agent | H11: Unknown
E12: Credential
E13: Knowledge source
E14: Memory
E15: System
E16: Human
E17: Organisation

Sheet Memory Controls
A1: Memory Controls
A2: One row per governed memory store. Memory can inform actions but never grants authority.
A4: AIR-ID | B4: AG-ID | C4: Memory ID | D4: Memory Type | E4: Read Scope | F4: Write Scope | G4: Provenance | H4: Retention | I4: Deletion / Erasure | J4: Isolation | K4: Poisoning Control | L4: Cross-Agent Sharing | M4: Authority Prohibited? | N4: Owner | O4: Evidence Ref

Sheet Tool Authority Registry
A1: Tool Authority Registry
A2: One row per tool/API/MCP/browser/shell capability available to the agent.
A4: AIR-ID | B4: AG-ID | C4: Tool ID | D4: Tool / Function | E4: Owner | F4: Data Accessed | G4: Permission | H4: Environment | I4: Maximum Impact | J4: Transaction / Financial Limit | K4: Reversibility | L4: Approval Requirement | M4: Monitoring | N4: Disable / Kill Mechanism | O4: Evidence Ref

Sheet Interface Register
A1: Interface Register
A2: Every API, MCP, browser, messaging, SaaS or agent-to-agent boundary is recorded.
A4: AIR-ID | B4: AG-ID | C4: Interface ID | D4: Interface Type | E4: Endpoint / System | F4: Direction | G4: Trust Boundary | H4: Authority Crossing | I4: Data Crossing | J4: Authentication | K4: Authorisation | L4: Validation | M4: Rate / Budget Limit | N4: Failure / Containment | O4: Evidence Ref

Sheet Runtime Controls
A1: Runtime Controls
A2: Required controls are operational only when Implemented and Evidenced (Actual State = Evidenced; “Implemented” alone is not enough), or when an authorised, time-bounded compensating control is recorded (Compensating Control completed and Expiry / Review a date on or after today; an expired control must be re-authorised; Playbook F.7.8, F.7.10). For action-capable agents, use the ASI01–ASI10 control IDs below where applicable and cite AIG-ASS-11 findings/tests. Set Required State per AIG-ASS-11 (Not applicable requires rationale there). A Core or Core plus features agent needs rows only for the controls AIG-ASS-11 marks Required; a Full-level agent (T3 and above) needs all ten rows, each Required or Not applicable; leave Actual State blank until assessed; test evidence is mandatory for Evidenced.
A4: AIR-ID | B4: AG-ID | C4: Control ID | D4: Control | E4: Required State | F4: Actual State | G4: Test Date | H4: Test Result | I4: Time to Containment | J4: Owner | K4: Evidence Ref | L4: Expiry / Review | M4: Compensating Control
C5: ASI01 | D5: Goal hijack / untrusted instruction boundary
C6: ASI02 | D6: Tool misuse / permitted action and limits
C7: ASI03 | D7: Agent identity / privilege / revocation
C8: ASI04 | D8: Model, tool, connector and MCP supply chain
C9: ASI05 | D9: Unexpected code execution boundaries
C10: ASI06 | D10: Persistent/shared memory and context poisoning
C11: ASI07 | D11: Authenticated inter-agent communication
C12: ASI08 | D12: Cascade, recursion, budget and containment
C13: ASI09 | D13: Human approval resistant to misleading agent output
C14: ASI10 | D14: Rogue behaviour / stop / forensic reconstruction

Sheet Agentic Action Records
A1: Agentic Action Records
A2: Sample / manual fallback for AIG-AGT-06 (normally generated by the platform). Per-action evidence for consequential activity, using the AIG-AGT-06 field list; do not capture private chain-of-thought.
A4: Action ID | B4: AIR-ID | C4: AG-ID | D4: UC-ID in scope for this action | E4: ASBOM record version | F4: Source Authority Edge ID(s) | G4: Agent Identity / Version | H4: Authority Invoked | I4: Use-specific authority / decision reference | J4: Objective / Context | K4: Action / Tool | L4: Policy Decision | M4: Approval / Override | N4: Timestamp | O4: Outcome | P4: Reversibility | Q4: External Side Effect | R4: Runtime control state | S4: Exception / incident / escalation ref | T4: Evidence Ref | U4: Review Required

Sheet Multi-Agent Controls
A1: Multi-Agent Controls
A2: Controls parent-child delegation, recursion, budgets and termination.
A4: AIR-ID | B4: Parent Agent (AG-ID) | C4: Child Agent (AG-ID) | D4: Delegation Depth | E4: Authority Ceiling | F4: Recursion Allowed | G4: Concurrent Agent Limit | H4: Budget / Transaction Ceiling | I4: Authentication | J4: Termination Rule | K4: Containment Propagation | L4: Evidence Ref

Sheet Governance Design Rules
A1: Rule | B1: Application
A2: Single source of truth | B2: Agent Record/ASBOM is the authoritative agentic record; do not duplicate authority data in separate forms.
A3: AIR-ID spine | B3: Every agentic record links to the existing AIR-ID; agentic governance is an extension of the AI lifecycle, not a second intake.
A4: Derived authority graph | B4: Authority Graph should be generated/refreshed from ASBOM authority/delegation edges where possible.
A5: Capture once | B5: Capability, autonomy, memory, interfaces, tools and delegation are recorded once and reused by assurance.
A6: Runtime boundary | B6: Platform/IAM/security implement enforcement; governance records requirements and evidence.
A7: No authority from memory | B7: Retrieved or remembered information never silently becomes authority to act.
A8: Proportionality | B8: Agentic controls are triggered by agency and consequence; not every AI requires an ASBOM.
A9: Production requirement (checked at Gate 6) | B9: Per Playbook F.7.8: a system-level move to Approved/Active (Governance Approval Status / Operational Status) is not a production decision and is not permission to use. Consequential autonomy may operate for a UC-ID only when the delegated decision for that UC-ID is recorded in AIG-DEC-03 (dated Gate Event in AIG-DEC-04) and each required runtime control is Implemented and Evidenced, or a time-bounded compensating control has been expressly accepted for that use by the relevant delegated authority, with owner, expiry, residual risk and evidence in AIG-DEC-03 and AIG-DEC-04. A control recorded as Designed or Specified is not operating; a scoped pilot is a separate decision; a deferred platform phase is not a waiver.

Sheet INTEGRATION INV-04 DEC-04
A1: AIG-AGT-04 — PROPOSED AIG-INV-04/AIG-DEC-04 INTEGRATION NOTES
A2: NOT APPROVED — additive integration annex only; existing workbook content and formulas are retained unchanged. AIG-INV-04 (AI Register) and AIG-DEC-04 (Gate Log) are themselves proposed designs: until the Council approves their adoption and migration, the Council’s existing records remain authoritative and the AIG-INV-04/AIG-DEC-04 joins below are design references only. No live system, event, evidence, approval or Council decision is asserted.
A4: Contract area | B4: Authoritative key / authority | C4: Link / required handling and trigger
A5: Stable agent key | B5: AG-ID is a permanent, unique, stable identifier for each individual agent; assign once under controlled governance, never derive from row number/name, recycle, or silently change it. AIR-ID remains the permanent system key. | C5: Agent Record carries AG-ID (column AY) and, from v0.3, every child sheet carries AG-ID beside AIR-ID. One agent per row; one AIR-ID may link to multiple AG-IDs. Keep each AG-ID linked to its parent AIR-ID.
A6: AIG-INV-04 portfolio join | B6: AIG-INV-04 AI Register remains the portfolio/system index keyed by AIR-ID; its Agent Record (AIG-AGT-04) Ref points to this ASBOM. The ASBOM is authoritative for per-agent identity, composition, authority envelope and permissions. | C6: Link AIG-INV-04 to AIG-AGT-04 using AIR-ID plus the AIG-AGT-04 reference; use AG-ID to identify the specific agent within the record. Do not duplicate or re-key the ASBOM permission/authority data in AIG-INV-04.
A7: Authority and permissions | B7: Agent Record and supporting ASBOM sheets (Capability Vector, Components, Authority & Delegations, tools, interfaces and controls) are authoritative for each agent’s actual approved permissions and constraints. A summary field is not a grant of authority. | C7: Enforcement belongs in the platform/IAM/runtime controls; record approved scope, limits, approvals, evidence and revocation here. Never infer permission from memory, a link, an AGPI priority, or another artefact.
A8: AIG-AGT-05 Authority Graph | B8: AIG-AGT-05 is a derived representation of ASBOM authority/delegation edges, not a second authority source. | C8: Reference the same AG-ID and AIR-ID; refresh/validate graph edges from ASBOM. Resolve conflicts against the authoritative AIG-AGT-04 record, not the graph.
A9: AIG-AGT-06 Action Decision Record | B9: AIG-AGT-06 records a particular agentic action/decision and its approvals/evidence; it does not redefine persistent agent permissions. | C9: Reference the stable AG-ID and parent AIR-ID on action evidence (and the applicable AIG-AGT-04 ASBOM record version, Agent Record column BB). Check each action against current ASBOM permissions; do not re-key the agent or copy authority as a new source.
A10: No re-keying / lifecycle | B10: AIR-ID continues to join system-wide AIG-INV-04/AIG-ASS-01/AIG-OPS-06/AIG-DEC-04/AIG-OPS-02 records. AG-ID is an additional per-agent key only; it does not replace AIR-ID or create a second intake. | C10: Carry both IDs in cross-record references where an individual agent is involved. Preserve IDs across name/version changes; use controlled retirement/successor traceability rather than reusing an ID.

Sheet STANDARDS SCOPE QA
A1: PROPOSED QA INDEX — NOT APPROVED. A source reference does not establish applicability or compliance. See AIG-AIMS-05 and AIG-AIMS-13; owners must validate the current source, case-specific scope, control evidence and adopted status.
A2: Requirement ID | B2: Instrument / edition | C2: Conditional scope / relevance | D2: Source URL | E2: Owner validation status
A3: REQ-001 | B3: UK General Data Protection Regulation (UK GDPR), as amended | C3: Where personal data is processed; test each UK GDPR provision separately. | D3: https://www.legislation.gov.uk/eur/2016/679/contents | E3: Specialist validation required
A4: REQ-023 | B4: Computer Misuse Act 1990 | C4: Screen the legislation requirement against this artefact's actual use and record evidence/version; see the AIG-AIMS-05 Applicable Requirements entry (REQ-023) for the controlled position. | D4: https://www.legislation.gov.uk/ukpga/1990/18/contents | E4: Specialist validation required
A5: REQ-039 | B5: NCSC Guidelines for Secure AI System Development | C5: Screen the government security guidance requirement against this artefact's actual use and record evidence/version; see the AIG-AIMS-05 Applicable Requirements entry (REQ-039) for the controlled position. | D5: https://www.ncsc.gov.uk/collection/guidelines-secure-ai-system-development/introduction | E5: Specialist validation required
A6: REQ-040 | B6: ISO/IEC 42001:2023 Artificial intelligence management system | C6: Proposed management-system design mapping; licensed clause review and adoption needed. | D6: https://www.iso.org/standard/42001 | E6: Specialist validation required
A7: NIST-AI-100-1 | B7: NIST AI Risk Management Framework 1.0 (NIST AI 100-1, January 2023) | C7: Voluntary alignment reference; not certification or statutory conformity | D7: https://www.nist.gov/publications/artificial-intelligence-risk-management-framework-ai-rmf-10 | E7: Voluntary alignment reference; not certification or statutory conformity
A8: OWASP-ACS-2026 | B8: OWASP Agent Control Standard (source edition/date to confirm) | C8: Technical design guidance; verify edition and operational tests | D8: https://genai.owasp.org/resource/agent-control-standard-acs/ | E8: Technical design guidance; verify edition and operational tests

Sheet MAP & SPLIT CONTRACT
A1: AIG-AGT-04 / PROPOSED THREE-ARTEFACT SOURCE CONTRACT
A3: Status | B3: PROPOSED INTEGRATION DESIGN ONLY. This sheet does not amend the artefact's native assessment, decision authority, data or formulas.
A4: Role of this file | B4: Agent Record: AIG-AGT-04 owns exact agent identity, mandate, tools, permissions and tested controls; map AG/TOOL components point to the exact AIG-AGT-04 row/version; AIG-AGT-05 owns derived authority paths. An AIR-ID may have multiple AG-IDs.
A5: AIG-INV-04 source | B5: Separate AIG-INV-04 AI Register: official AIR-ID, current position, in-file Assessment summary/Evidence index. Reconcile against authoritative AIG-INV-04 before using a copied value.
A6: AIG-DEC-04 source | B6: Separate AIG-DEC-04 Gate Log: prospective Gate plan, dated Gate events, event-linked Conditions. A planned gate is not a decision. A decision requires AIG-DEC-03 or approved minutes and proper delegation.
A7: Map source | B7: Proposed standalone Capabilities and System Map (candidate catalogue ID AIG-INV-05): UC/CAP and component relationship pointers. Edge ID is not an approval or permission; AIG-AGT-04/AIG-AGT-05 remain sources of agent scope/authority.
A8: Data exchange | B8: Use controlled AIR-ID across files. Where applicable reference exact Event ID, Condition ID, Evidence ID, AG-ID and Edge ID. Record source file/version/as-at with imported or quoted evidence; no live cross-workbook formula is assumed.
A9: Change trigger | B9: New or expanded system/tool access, or a material model, data, interface, purpose or agent change: log the map change, obtain owner reassessment and escalate to the proper AIG-DEC-04 gate/AIG-DEC-03 decision when required.
A10: Validation before use | B10: The INTEGRATION INV-04 DEC-04 tab in this workbook is current supporting design guidance (not historical) and holds the detailed join notes. Controlled owners must reconcile real records, validate values and formulas in Excel, and approve migration/cutover; existing Council records remain unchanged until then.
